{
    "name": "Thairath",
    "image_profile": "https://instagram.fbkk2-8.fna.fbcdn.net/v/t51.2885-19/s150x150/93249003_2699080507045626_9034629849355911168_n.jpg?_nc_ht=instagram.fbkk2-8.fna.fbcdn.net&_nc_ohc=FQE-HsuwsYEAX8Sgb8V&oh=4b0febbd6cddf35ff01826c2e0c9fa8f&oe=5FB53F69",
    "image_profile_hd": "https://instagram.fbkk2-8.fna.fbcdn.net/v/t51.2885-19/s320x320/93249003_2699080507045626_9034629849355911168_n.jpg?_nc_ht=instagram.fbkk2-8.fna.fbcdn.net&_nc_ohc=FQE-HsuwsYEAX8Sgb8V&oh=fdb12c70ae9a26d9e7b388059d1a2324&oe=5FB4A391",
    "newsPost": {
        "count": 48444,
        "edges": [
            {
                "_id": "2421735091008372076",
                "display": "https://instagram.fbkk2-8.fna.fbcdn.net/v/t51.2885-15/fr/e15/s1080x1080/121635968_671787536782848_639277938228653159_n.jpg?_nc_ht=instagram.fbkk2-8.fna.fbcdn.net&_nc_cat=100&_nc_ohc=PcC7qBueGqcAX9y4_LT&oh=44454baba51a4fedc5c40ee9a786223e&oe=5FB2BFF7",
                "type": "post",
                "caption": [
                    {
                        "node": {
                            "text": "17 ตุลาคม : พบสามีภรรยาชาวเมียนมา อาศัยอยู่ใน อ.แม่สอด จ.ตาก ติดเชื้อโควิด-19 อีก 2 คน คาดติดจากลูกชายที่ทำงานใกล้ชิดกับคนขับรถชาวเมียนมา ที่ตรวจพบติดเชื้อก่อนหน้านี้ โดยการตรวจพบครั้งนี้เกิดจากการตรวจแบบค้นหาเชิงรุกในชุมชน\n⁣\nส่วนผู้ติดเชื้อเพิ่ม 8 ราย เป็นผู้ที่เดินทางมาจากต่างประเทศ และเข้า State Quarantine⁣⁣⁣⁣ \n▪ เนปาล 1⁣\n▪ สหรัฐอาหรับเอมิเรตส์ 1⁣\n▪ ญี่ปุ่น 1⁣\n▪ สหรัฐอเมริกา 1\n▪️โปแลนด์​ 1\n▪ สหราชอาณาจักร 3⁣\n⁣\n#โควิด19 #COVID19 #ไทยรัฐออนไลน์ #Thairath"
                        }
                    }
                ],
                "thumbnail_src": "https://instagram.fbkk2-8.fna.fbcdn.net/v/t51.2885-15/sh0.08/e35/s640x640/121635968_671787536782848_639277938228653159_n.jpg?_nc_ht=instagram.fbkk2-8.fna.fbcdn.net&_nc_cat=100&_nc_ohc=PcC7qBueGqcAX9y4_LT&_nc_tp=24&oh=f78186be2103ee947c26e9a803e81de6&oe=5FB58D4D",
                "thumbnail_resources": [
                    {
                        "src": "https://instagram.fbkk2-8.fna.fbcdn.net/v/t51.2885-15/e15/s150x150/121635968_671787536782848_639277938228653159_n.jpg?_nc_ht=instagram.fbkk2-8.fna.fbcdn.net&_nc_cat=100&_nc_ohc=PcC7qBueGqcAX9y4_LT&_nc_tp=15&oh=b114eef7de0fff9399cb1180efac9a2e&oe=5FB5964B",
                        "config_width": 150,
                        "config_height": 150
                    },
                    {
                        "src": "https://instagram.fbkk2-8.fna.fbcdn.net/v/t51.2885-15/e15/s240x240/121635968_671787536782848_639277938228653159_n.jpg?_nc_ht=instagram.fbkk2-8.fna.fbcdn.net&_nc_cat=100&_nc_ohc=PcC7qBueGqcAX9y4_LT&_nc_tp=15&oh=e1530cf219717bc845dea26e18fe3a45&oe=5FB53B01",
                        "config_width": 240,
                        "config_height": 240
                    },
                    {
                        "src": "https://instagram.fbkk2-8.fna.fbcdn.net/v/t51.2885-15/e15/s320x320/121635968_671787536782848_639277938228653159_n.jpg?_nc_ht=instagram.fbkk2-8.fna.fbcdn.net&_nc_cat=100&_nc_ohc=PcC7qBueGqcAX9y4_LT&_nc_tp=15&oh=e3eb8b2bf53579fbbd9dd0cb2cebfb98&oe=5FB53E3B",
                        "config_width": 320,
                        "config_height": 320
                    },
                    {
                        "src": "https://instagram.fbkk2-8.fna.fbcdn.net/v/t51.2885-15/e15/s480x480/121635968_671787536782848_639277938228653159_n.jpg?_nc_ht=instagram.fbkk2-8.fna.fbcdn.net&_nc_cat=100&_nc_ohc=PcC7qBueGqcAX9y4_LT&_nc_tp=15&oh=3f4e4f33fa81dc4b934d81da05018bc5&oe=5FB5C961",
                        "config_width": 480,
                        "config_height": 480
                    },
                    {
                        "src": "https://instagram.fbkk2-8.fna.fbcdn.net/v/t51.2885-15/sh0.08/e35/s640x640/121635968_671787536782848_639277938228653159_n.jpg?_nc_ht=instagram.fbkk2-8.fna.fbcdn.net&_nc_cat=100&_nc_ohc=PcC7qBueGqcAX9y4_LT&_nc_tp=24&oh=f78186be2103ee947c26e9a803e81de6&oe=5FB58D4D",
                        "config_width": 640,
                        "config_height": 640
                    }
                ]
            },
            {
                "_id": "2421729276703554019",
                "display": "https://instagram.fbkk2-7.fna.fbcdn.net/v/t51.2885-15/fr/e15/s1080x1080/121585279_947907355736528_6791095768254692660_n.jpg?_nc_ht=instagram.fbkk2-7.fna.fbcdn.net&_nc_cat=108&_nc_ohc=FYxFrSE91woAX8tXSbH&oh=3a140de47f991196756833827ecad45a&oe=5FB388DF",
                "type": "post",
                "caption": [
                    {
                        "node": {
                            "text": "ม็อบเคลื่อนไหวแล้ว แจ้งรวมพลที่สถานีรถไฟฟ้าทุกแห่ง เวลาบ่าย 3 โมง⁣\n⁣\n17 ตุลาคม : เมื่อเวลาประมาณ 11.00 น. แฟนเพจ แนวร่วมธรรมศาสตร์และการชุมนุม - United Front of Thammasat and Demonstration ได้โพสต์ข้อความว่า ภายในเวลา 15.00 น. ขอให้ทุกคนเตรียมตัวประจำการได้ที่สถานีรถไฟฟ้าทุกแห่ง คำแนะนำในกรณีที่มีการหยุดการเดินรถไฟฟ้าก่อนเริ่มนัดหมาย ขอให้ทุกคนใช้มาตรการดังต่อไปนี้ \"สถานีรถไฟฟ้าทุกสถานีคือสถานที่ชุมนุม\"⁣\n⁣\n#ม็อบ17ตุลา #เกาะติดชุมนุม63 #ไทยรัฐออนไลน์ #Thairath"
                        }
                    }
                ],
                "thumbnail_src": "https://instagram.fbkk2-7.fna.fbcdn.net/v/t51.2885-15/sh0.08/e35/s640x640/121585279_947907355736528_6791095768254692660_n.jpg?_nc_ht=instagram.fbkk2-7.fna.fbcdn.net&_nc_cat=108&_nc_ohc=FYxFrSE91woAX8tXSbH&_nc_tp=24&oh=e20a2277b957903e5adbed211f166d74&oe=5FB2C018",
                "thumbnail_resources": [
                    {
                        "src": "https://instagram.fbkk2-7.fna.fbcdn.net/v/t51.2885-15/e15/s150x150/121585279_947907355736528_6791095768254692660_n.jpg?_nc_ht=instagram.fbkk2-7.fna.fbcdn.net&_nc_cat=108&_nc_ohc=FYxFrSE91woAX8tXSbH&_nc_tp=15&oh=eb9bc0321ce44d3dcff2fe7419b51f06&oe=5FB22AAB",
                        "config_width": 150,
                        "config_height": 150
                    },
                    {
                        "src": "https://instagram.fbkk2-7.fna.fbcdn.net/v/t51.2885-15/e15/s240x240/121585279_947907355736528_6791095768254692660_n.jpg?_nc_ht=instagram.fbkk2-7.fna.fbcdn.net&_nc_cat=108&_nc_ohc=FYxFrSE91woAX8tXSbH&_nc_tp=15&oh=3f242805d25e23b08392a21883d8dff2&oe=5FB24EAD",
                        "config_width": 240,
                        "config_height": 240
                    },
                    {
                        "src": "https://instagram.fbkk2-7.fna.fbcdn.net/v/t51.2885-15/e15/s320x320/121585279_947907355736528_6791095768254692660_n.jpg?_nc_ht=instagram.fbkk2-7.fna.fbcdn.net&_nc_cat=108&_nc_ohc=FYxFrSE91woAX8tXSbH&_nc_tp=15&oh=32672b5db690c33f77f3099f2f4cbb9c&oe=5FB4EA53",
                        "config_width": 320,
                        "config_height": 320
                    },
                    {
                        "src": "https://instagram.fbkk2-7.fna.fbcdn.net/v/t51.2885-15/e15/s480x480/121585279_947907355736528_6791095768254692660_n.jpg?_nc_ht=instagram.fbkk2-7.fna.fbcdn.net&_nc_cat=108&_nc_ohc=FYxFrSE91woAX8tXSbH&_nc_tp=15&oh=c4e677c030e5335b58c98a185d4d215e&oe=5FB45B96",
                        "config_width": 480,
                        "config_height": 480
                    },
                    {
                        "src": "https://instagram.fbkk2-7.fna.fbcdn.net/v/t51.2885-15/sh0.08/e35/s640x640/121585279_947907355736528_6791095768254692660_n.jpg?_nc_ht=instagram.fbkk2-7.fna.fbcdn.net&_nc_cat=108&_nc_ohc=FYxFrSE91woAX8tXSbH&_nc_tp=24&oh=e20a2277b957903e5adbed211f166d74&oe=5FB2C018",
                        "config_width": 640,
                        "config_height": 640
                    }
                ]
            },
            {
                "_id": "2421680764560601222",
                "display": "https://instagram.fbkk2-8.fna.fbcdn.net/v/t51.2885-15/fr/e15/s1080x1080/121512827_677216033178701_7332816764169185031_n.jpg?_nc_ht=instagram.fbkk2-8.fna.fbcdn.net&_nc_cat=1&_nc_ohc=t-wgHhtd8ecAX-sCWY2&oh=3a9831b77697198419678a4309739502&oe=5FB5E51A",
                "type": "post",
                "caption": [
                    {
                        "node": {
                            "text": "“คณะราษฎร” ออกแถลงการณ์ ประณามการใช้ความรุนแรงสลายชุมนุม ยืนยันเดินหน้าจัดชุมนุมต่อในวันนี้⁣⁣\n⁣⁣\n17 ตุลาคม : เมื่อเวลา 06.00 น. เฟซบุ๊ก กลุ่มฟื้นฟูประชาธิปไตย Democracy Restoration Group - DRG โพสต์ข้อความ โดยมีเนื้อหาระบุว่า แถลงการณ์จาก (คณะ) ราษฎร จากเหตุการณ์สลายการชุมนุมที่เกิดขึ้นเมื่อตอนค่ำของวันที่ 16 ตุลาคม 2563 ที่ผ่านมา เรารับรู้ได้ว่ารัฐบาลและกองทัพ ตั้งตนเป็นปฏิปักษ์ต่อประชาชนอย่างสมบูรณ์ เราของประณามทุกการกระทำที่ใช้ความรุนแรงกับประชาชน และขอประณามทุกคนที่มีส่วนเกี่ยวข้อง ไม่ว่าจะทางตรงหรือทางอ้อม⁣⁣\n⁣⁣\nเราขอประกาศว่า เรายังยืนยันที่จะจัดการชุมนุมต่อไปในวันที่ 17 ตุลาคม 2563 ต่อให้รัฐบาลจะทำการจับกุมแกนนำของเราไปจนหมด แต่เหตุการณ์ที่ผ่านมาในช่วงสองวันนี้ พิสูจน์ให้เห็นแล้วว่าแกนนำที่แท้จริงนั้นคือ \"ประชาชนทุกคน\" มิใช่เพียงคนใดคนหนึ่ง ประชาชนไม่อาจทนต่อการกดขี่ได้ฉันใด ชนชั้นนำก็ไม่อาจฝืนสายธารแห่งการเปลี่ยนแปลงได้ฉันนั้น หากรัฐยังคงเพิกเฉยต่อข้อเรียกร้องของเรา ก็พึงรู้ไว้เถิดว่าเราเองก็ไม่สามารถละทิ้งอุดมการณ์ได้เช่นกัน⁣⁣\n⁣⁣\nจากนี้จะไม่มีคณะราษฎร จะมีเพียงแต่ \"ราษฎร\" เท่านั้น ขอย้ำในจุดยืนว่าทุกคนคือแกนนำ และขอเชิญชวนให้ทุกท่านที่พร้อม ออกมารวมตัวกันอีกครั้งในวันนี้ เวลา 16.00 น.⁣⁣\n⁣⁣\nขอให้ทุกท่านติดตามรายละเอียดของสถานที่อย่างใกล้ชิด เตรียมกายและใจให้พร้อมกับการชุมนุมในวันนี้ และรับมือกับการสลายการชุมนุมที่อาจเกิดขึ้น⁣⁣\n⁣\n\"คนยังคงยืนเด่นโดยท้าทาย แม้ผืนฟ้ามืดดับเดือนลับละลาย ดาวยังพรายศรัทธาเย้ยฟ้าดิน ดาวยังพรายอยู่จนฟ้ารุ่งราง\"⁣\n⁣\n#เกาะติดชุมนุม63 #ม็อบ17ตุลา #ไทยรัฐออนไลน์ #Thairath"
                        }
                    }
                ],
                "thumbnail_src": "https://instagram.fbkk2-8.fna.fbcdn.net/v/t51.2885-15/sh0.08/e35/s640x640/121512827_677216033178701_7332816764169185031_n.jpg?_nc_ht=instagram.fbkk2-8.fna.fbcdn.net&_nc_cat=1&_nc_ohc=t-wgHhtd8ecAX-sCWY2&_nc_tp=24&oh=f72226d0477a766e21fd5c55d08ebe3e&oe=5FB31451",
                "thumbnail_resources": [
                    {
                        "src": "https://instagram.fbkk2-8.fna.fbcdn.net/v/t51.2885-15/e15/s150x150/121512827_677216033178701_7332816764169185031_n.jpg?_nc_ht=instagram.fbkk2-8.fna.fbcdn.net&_nc_cat=1&_nc_ohc=t-wgHhtd8ecAX-sCWY2&_nc_tp=15&oh=b1c6cedc6b6f60d7423bb076a1c09918&oe=5FB3216E",
                        "config_width": 150,
                        "config_height": 150
                    },
                    {
                        "src": "https://instagram.fbkk2-8.fna.fbcdn.net/v/t51.2885-15/e15/s240x240/121512827_677216033178701_7332816764169185031_n.jpg?_nc_ht=instagram.fbkk2-8.fna.fbcdn.net&_nc_cat=1&_nc_ohc=t-wgHhtd8ecAX-sCWY2&_nc_tp=15&oh=19599b3571a4e5bd05adcf2fb49034f3&oe=5FB3796C",
                        "config_width": 240,
                        "config_height": 240
                    },
                    {
                        "src": "https://instagram.fbkk2-8.fna.fbcdn.net/v/t51.2885-15/e15/s320x320/121512827_677216033178701_7332816764169185031_n.jpg?_nc_ht=instagram.fbkk2-8.fna.fbcdn.net&_nc_cat=1&_nc_ohc=t-wgHhtd8ecAX-sCWY2&_nc_tp=15&oh=0d1236e4aef2233d880c8632b22f1787&oe=5FB3F616",
                        "config_width": 320,
                        "config_height": 320
                    },
                    {
                        "src": "https://instagram.fbkk2-8.fna.fbcdn.net/v/t51.2885-15/e15/s480x480/121512827_677216033178701_7332816764169185031_n.jpg?_nc_ht=instagram.fbkk2-8.fna.fbcdn.net&_nc_cat=1&_nc_ohc=t-wgHhtd8ecAX-sCWY2&_nc_tp=15&oh=8c28330b1292222556c734b79e023ab9&oe=5FB44DD3",
                        "config_width": 480,
                        "config_height": 480
                    },
                    {
                        "src": "https://instagram.fbkk2-8.fna.fbcdn.net/v/t51.2885-15/sh0.08/e35/s640x640/121512827_677216033178701_7332816764169185031_n.jpg?_nc_ht=instagram.fbkk2-8.fna.fbcdn.net&_nc_cat=1&_nc_ohc=t-wgHhtd8ecAX-sCWY2&_nc_tp=24&oh=f72226d0477a766e21fd5c55d08ebe3e&oe=5FB31451",
                        "config_width": 640,
                        "config_height": 640
                    }
                ]
            },
            {
                "_id": "2421668552097439758",
                "display": "https://instagram.fbkk2-8.fna.fbcdn.net/v/t51.2885-15/fr/e15/s1080x1080/121674502_2756266647962455_4269521038892334227_n.jpg?_nc_ht=instagram.fbkk2-8.fna.fbcdn.net&_nc_cat=1&_nc_ohc=uFyj2iiO1R8AX8U9B7c&oh=033bc7c55792af3bcfddffbd4b7abfc7&oe=5FB46684",
                "type": "post",
                "caption": [
                    {
                        "node": {
                            "text": "โจชัว หว่อง ชู 3 นิ้ว ติดแฮชแท็ก #StandWithThailand ให้กำลังใจคนไทย⁣\n⁣\n17 ตุลาคม : นายโจชัว หว่อง นักเคลื่อนไหวเรียกร้องประชาธิปไตยชาวฮ่องกง วัย 23 ปี ทวีตข้อความผ่าน @joshuawongcf เป็นภาษาไทยว่า ผมขอเป็นกำลังใจให้ชาวไทยทุกคนนะครับ #MilkTeaAlliance⁣\n⁣\nโดยก่อนหน้านี้ นายโจชัว หว่อง ได้เผยภาพตัวเองชู 3 นิ้ว พร้อมกับทวีตข้อความว่า #StandWithThailand #MilkTeaAliance พร้อมกับประโยคดังจากภาพยนตร์เรื่อง V for Vendetta ที่ระบุว่า \"ประชาชนไม่ควรกลัวรัฐบาล รัฐบาลต่างหากที่ต้องกลัวประชาชน\"⁣\n⁣\n#เกาะติดชุมนุม63 #ชุมนุมแยกปทุมวัน #ไทยรัฐออนไลน์ #Thairath"
                        }
                    }
                ],
                "thumbnail_src": "https://instagram.fbkk2-8.fna.fbcdn.net/v/t51.2885-15/sh0.08/e35/s640x640/121674502_2756266647962455_4269521038892334227_n.jpg?_nc_ht=instagram.fbkk2-8.fna.fbcdn.net&_nc_cat=1&_nc_ohc=uFyj2iiO1R8AX8U9B7c&_nc_tp=24&oh=f595d458b611f8e47f23669deb03ffd8&oe=5FB5C288",
                "thumbnail_resources": [
                    {
                        "src": "https://instagram.fbkk2-8.fna.fbcdn.net/v/t51.2885-15/e15/s150x150/121674502_2756266647962455_4269521038892334227_n.jpg?_nc_ht=instagram.fbkk2-8.fna.fbcdn.net&_nc_cat=1&_nc_ohc=uFyj2iiO1R8AX8U9B7c&_nc_tp=15&oh=76ccc691fa9cefdd8bcd112e208558d9&oe=5FB4BE9A",
                        "config_width": 150,
                        "config_height": 150
                    },
                    {
                        "src": "https://instagram.fbkk2-8.fna.fbcdn.net/v/t51.2885-15/e15/s240x240/121674502_2756266647962455_4269521038892334227_n.jpg?_nc_ht=instagram.fbkk2-8.fna.fbcdn.net&_nc_cat=1&_nc_ohc=uFyj2iiO1R8AX8U9B7c&_nc_tp=15&oh=4a80b79a79f6d4c004a98fe9a181f1a5&oe=5FB49852",
                        "config_width": 240,
                        "config_height": 240
                    },
                    {
                        "src": "https://instagram.fbkk2-8.fna.fbcdn.net/v/t51.2885-15/e15/s320x320/121674502_2756266647962455_4269521038892334227_n.jpg?_nc_ht=instagram.fbkk2-8.fna.fbcdn.net&_nc_cat=1&_nc_ohc=uFyj2iiO1R8AX8U9B7c&_nc_tp=15&oh=373d226d21eaba7246327dc6cdce6318&oe=5FB4880F",
                        "config_width": 320,
                        "config_height": 320
                    },
                    {
                        "src": "https://instagram.fbkk2-8.fna.fbcdn.net/v/t51.2885-15/e15/s480x480/121674502_2756266647962455_4269521038892334227_n.jpg?_nc_ht=instagram.fbkk2-8.fna.fbcdn.net&_nc_cat=1&_nc_ohc=uFyj2iiO1R8AX8U9B7c&_nc_tp=15&oh=4236cb78614ccc92811afc0921b0c51f&oe=5FB4F3CD",
                        "config_width": 480,
                        "config_height": 480
                    },
                    {
                        "src": "https://instagram.fbkk2-8.fna.fbcdn.net/v/t51.2885-15/sh0.08/e35/s640x640/121674502_2756266647962455_4269521038892334227_n.jpg?_nc_ht=instagram.fbkk2-8.fna.fbcdn.net&_nc_cat=1&_nc_ohc=uFyj2iiO1R8AX8U9B7c&_nc_tp=24&oh=f595d458b611f8e47f23669deb03ffd8&oe=5FB5C288",
                        "config_width": 640,
                        "config_height": 640
                    }
                ]
            },
            {
                "_id": "2421585464429121744",
                "display": "https://instagram.fbkk2-8.fna.fbcdn.net/v/t51.2885-15/e35/121506552_204019467813597_654662730708296682_n.jpg?_nc_ht=instagram.fbkk2-8.fna.fbcdn.net&_nc_cat=1&_nc_ohc=kKpIo6MvcZ4AX913lSm&_nc_tp=18&oh=27dfcda68831bc57d60bae154deffa9b&oe=5FB44286",
                "type": "post",
                "caption": [
                    {
                        "node": {
                            "text": "ดวงวันนี้มาแล้วจ้า\nดูดวงไทยรัฐโดยหมอดูชื่อดังรวมไว้ที่นี่>>\nwww.thairath.co.th/horoscope\n#horoscope #ดวงไทยรัฐ #ไทยรัฐออนไลน์ #Thairath"
                        }
                    }
                ],
                "thumbnail_src": "https://instagram.fbkk2-8.fna.fbcdn.net/v/t51.2885-15/sh0.08/e35/s640x640/121506552_204019467813597_654662730708296682_n.jpg?_nc_ht=instagram.fbkk2-8.fna.fbcdn.net&_nc_cat=1&_nc_ohc=kKpIo6MvcZ4AX913lSm&_nc_tp=24&oh=ff6c2324e3e2a0cfa36fb009faa6f6b3&oe=5FB21AE1",
                "thumbnail_resources": [
                    {
                        "src": "https://instagram.fbkk2-8.fna.fbcdn.net/v/t51.2885-15/e35/s150x150/121506552_204019467813597_654662730708296682_n.jpg?_nc_ht=instagram.fbkk2-8.fna.fbcdn.net&_nc_cat=1&_nc_ohc=kKpIo6MvcZ4AX913lSm&_nc_tp=15&oh=0d3720e9fe06b62e11f43e5b107e3261&oe=5FB3D248",
                        "config_width": 150,
                        "config_height": 150
                    },
                    {
                        "src": "https://instagram.fbkk2-8.fna.fbcdn.net/v/t51.2885-15/e35/s240x240/121506552_204019467813597_654662730708296682_n.jpg?_nc_ht=instagram.fbkk2-8.fna.fbcdn.net&_nc_cat=1&_nc_ohc=kKpIo6MvcZ4AX913lSm&_nc_tp=15&oh=9b6d027c93dfa0f1ce61e9a76e61ca2b&oe=5FB3B00E",
                        "config_width": 240,
                        "config_height": 240
                    },
                    {
                        "src": "https://instagram.fbkk2-8.fna.fbcdn.net/v/t51.2885-15/e35/s320x320/121506552_204019467813597_654662730708296682_n.jpg?_nc_ht=instagram.fbkk2-8.fna.fbcdn.net&_nc_cat=1&_nc_ohc=kKpIo6MvcZ4AX913lSm&_nc_tp=15&oh=25b820edbffff313386a8c3936083b7b&oe=5FB4E9B8",
                        "config_width": 320,
                        "config_height": 320
                    },
                    {
                        "src": "https://instagram.fbkk2-8.fna.fbcdn.net/v/t51.2885-15/e35/s480x480/121506552_204019467813597_654662730708296682_n.jpg?_nc_ht=instagram.fbkk2-8.fna.fbcdn.net&_nc_cat=1&_nc_ohc=kKpIo6MvcZ4AX913lSm&_nc_tp=15&oh=ef0a4cf6d2f5adbaa0d2571b8276fa3e&oe=5FB29E6E",
                        "config_width": 480,
                        "config_height": 480
                    },
                    {
                        "src": "https://instagram.fbkk2-8.fna.fbcdn.net/v/t51.2885-15/sh0.08/e35/s640x640/121506552_204019467813597_654662730708296682_n.jpg?_nc_ht=instagram.fbkk2-8.fna.fbcdn.net&_nc_cat=1&_nc_ohc=kKpIo6MvcZ4AX913lSm&_nc_tp=24&oh=ff6c2324e3e2a0cfa36fb009faa6f6b3&oe=5FB21AE1",
                        "config_width": 640,
                        "config_height": 640
                    }
                ]
            },
            {
                "_id": "2421577961543035079",
                "display": "https://instagram.fbkk2-8.fna.fbcdn.net/v/t51.2885-15/e35/s1080x1080/121578245_346264319978564_6574788253509298569_n.jpg?_nc_ht=instagram.fbkk2-8.fna.fbcdn.net&_nc_cat=1&_nc_ohc=O1f9Fo3vbXgAX9k-M-2&_nc_tp=15&oh=d84c43266385c58cf15fde3b45fe11c7&oe=5FB5E7D4",
                "type": "post",
                "caption": [
                    {
                        "node": {
                            "text": "เท้าเปื้อนล้างง่าย​ แต่ใจเปื้อนล้างยาก​ จิตที่ตั้งไว้ผิด​ จะย้อนกลับมาทำร้ายตัวเรา​ ยิ่งกว่าศัตรูคู่เวร​- หลวงตามหาบัว\n#ธรรมะเช้านี้​ #ไทยรัฐออนไลน์ #Thairath"
                        }
                    }
                ],
                "thumbnail_src": "https://instagram.fbkk2-8.fna.fbcdn.net/v/t51.2885-15/sh0.08/e35/s640x640/121578245_346264319978564_6574788253509298569_n.jpg?_nc_ht=instagram.fbkk2-8.fna.fbcdn.net&_nc_cat=1&_nc_ohc=O1f9Fo3vbXgAX9k-M-2&_nc_tp=24&oh=143ee93887c83346560a1f123efe5af9&oe=5FB44B18",
                "thumbnail_resources": [
                    {
                        "src": "https://instagram.fbkk2-8.fna.fbcdn.net/v/t51.2885-15/e35/s150x150/121578245_346264319978564_6574788253509298569_n.jpg?_nc_ht=instagram.fbkk2-8.fna.fbcdn.net&_nc_cat=1&_nc_ohc=O1f9Fo3vbXgAX9k-M-2&_nc_tp=15&oh=1e660cf10fe8b6e76f0973ab1e76b5ee&oe=5FB5CB13",
                        "config_width": 150,
                        "config_height": 150
                    },
                    {
                        "src": "https://instagram.fbkk2-8.fna.fbcdn.net/v/t51.2885-15/e35/s240x240/121578245_346264319978564_6574788253509298569_n.jpg?_nc_ht=instagram.fbkk2-8.fna.fbcdn.net&_nc_cat=1&_nc_ohc=O1f9Fo3vbXgAX9k-M-2&_nc_tp=15&oh=eeecad5db8a35ec1842b2d54188fe44e&oe=5FB38715",
                        "config_width": 240,
                        "config_height": 240
                    },
                    {
                        "src": "https://instagram.fbkk2-8.fna.fbcdn.net/v/t51.2885-15/e35/s320x320/121578245_346264319978564_6574788253509298569_n.jpg?_nc_ht=instagram.fbkk2-8.fna.fbcdn.net&_nc_cat=1&_nc_ohc=O1f9Fo3vbXgAX9k-M-2&_nc_tp=15&oh=1e513d6b219f17ec5e28e4b42a34948c&oe=5FB567EB",
                        "config_width": 320,
                        "config_height": 320
                    },
                    {
                        "src": "https://instagram.fbkk2-8.fna.fbcdn.net/v/t51.2885-15/e35/s480x480/121578245_346264319978564_6574788253509298569_n.jpg?_nc_ht=instagram.fbkk2-8.fna.fbcdn.net&_nc_cat=1&_nc_ohc=O1f9Fo3vbXgAX9k-M-2&_nc_tp=15&oh=4dfacba6938fddbbb19dd410bcf3bd16&oe=5FB4D2AE",
                        "config_width": 480,
                        "config_height": 480
                    },
                    {
                        "src": "https://instagram.fbkk2-8.fna.fbcdn.net/v/t51.2885-15/sh0.08/e35/s640x640/121578245_346264319978564_6574788253509298569_n.jpg?_nc_ht=instagram.fbkk2-8.fna.fbcdn.net&_nc_cat=1&_nc_ohc=O1f9Fo3vbXgAX9k-M-2&_nc_tp=24&oh=143ee93887c83346560a1f123efe5af9&oe=5FB44B18",
                        "config_width": 640,
                        "config_height": 640
                    }
                ]
            },
            {
                "_id": "2421562954179768542",
                "display": "https://instagram.fbkk2-8.fna.fbcdn.net/v/t51.2885-15/e35/s1080x1080/121618457_177506130575988_7876579334106842469_n.jpg?_nc_ht=instagram.fbkk2-8.fna.fbcdn.net&_nc_cat=1&_nc_ohc=KSMsQx0OfTcAX-VxWaL&_nc_tp=15&oh=3b7edcf75376e0f204eab97acd82c8a1&oe=5FB57484",
                "type": "post",
                "caption": [
                    {
                        "node": {
                            "text": "หน้า 1 #นสพ #ไทยรัฐ ฉบับวันที่​ 17 ต.ค. 63\n🌟​​​​​​​​​​ตำรวจใช้รถฉีดน้ำแรงดันสูงถล่มม็อบ​กระเจิงสลายตัว​\n🌟​​พิษ​ 'นังกา'​ ดินถล่มเขาใหญ่\n🌟​ให้ชาติยุโรป​ยกระดับต้านโควิด\nอ่านข่าวทั้งหมดได้ที่ : www.thairath.co.th\n#หน้าหนึ่งไทยรัฐ​ #newspaper #Thairath"
                        }
                    }
                ],
                "thumbnail_src": "https://instagram.fbkk2-8.fna.fbcdn.net/v/t51.2885-15/sh0.08/e35/s640x640/121618457_177506130575988_7876579334106842469_n.jpg?_nc_ht=instagram.fbkk2-8.fna.fbcdn.net&_nc_cat=1&_nc_ohc=KSMsQx0OfTcAX-VxWaL&_nc_tp=24&oh=b45860f94f7066bf1994f62fa3bf2aa1&oe=5FB2C048",
                "thumbnail_resources": [
                    {
                        "src": "https://instagram.fbkk2-8.fna.fbcdn.net/v/t51.2885-15/e35/s150x150/121618457_177506130575988_7876579334106842469_n.jpg?_nc_ht=instagram.fbkk2-8.fna.fbcdn.net&_nc_cat=1&_nc_ohc=KSMsQx0OfTcAX-VxWaL&_nc_tp=15&oh=6606acd88d8c0ab1fc3d6ec2fbdbafaa&oe=5FB44A43",
                        "config_width": 150,
                        "config_height": 150
                    },
                    {
                        "src": "https://instagram.fbkk2-8.fna.fbcdn.net/v/t51.2885-15/e35/s240x240/121618457_177506130575988_7876579334106842469_n.jpg?_nc_ht=instagram.fbkk2-8.fna.fbcdn.net&_nc_cat=1&_nc_ohc=KSMsQx0OfTcAX-VxWaL&_nc_tp=15&oh=9daa13a1a3cf85dfbab5a0dacbc499ad&oe=5FB2F0C5",
                        "config_width": 240,
                        "config_height": 240
                    },
                    {
                        "src": "https://instagram.fbkk2-8.fna.fbcdn.net/v/t51.2885-15/e35/s320x320/121618457_177506130575988_7876579334106842469_n.jpg?_nc_ht=instagram.fbkk2-8.fna.fbcdn.net&_nc_cat=1&_nc_ohc=KSMsQx0OfTcAX-VxWaL&_nc_tp=15&oh=33252755bb1dd28e9757f59dc713cd50&oe=5FB53ABB",
                        "config_width": 320,
                        "config_height": 320
                    },
                    {
                        "src": "https://instagram.fbkk2-8.fna.fbcdn.net/v/t51.2885-15/e35/s480x480/121618457_177506130575988_7876579334106842469_n.jpg?_nc_ht=instagram.fbkk2-8.fna.fbcdn.net&_nc_cat=1&_nc_ohc=KSMsQx0OfTcAX-VxWaL&_nc_tp=15&oh=4e835ee3129681ebf1f553e90ecce37e&oe=5FB3EF7E",
                        "config_width": 480,
                        "config_height": 480
                    },
                    {
                        "src": "https://instagram.fbkk2-8.fna.fbcdn.net/v/t51.2885-15/sh0.08/e35/s640x640/121618457_177506130575988_7876579334106842469_n.jpg?_nc_ht=instagram.fbkk2-8.fna.fbcdn.net&_nc_cat=1&_nc_ohc=KSMsQx0OfTcAX-VxWaL&_nc_tp=24&oh=b45860f94f7066bf1994f62fa3bf2aa1&oe=5FB2C048",
                        "config_width": 640,
                        "config_height": 640
                    }
                ]
            },
            {
                "_id": "2421342019460032471",
                "display": "https://instagram.fbkk2-8.fna.fbcdn.net/v/t51.2885-15/e35/s1080x1080/121500887_2680430278842021_5580307661557774015_n.jpg?_nc_ht=instagram.fbkk2-8.fna.fbcdn.net&_nc_cat=1&_nc_ohc=U40LhN82PzoAX9DHZW-&_nc_tp=15&oh=eb53595259bf442c1e4ec472d60a14af&oe=5FB3BFAF",
                "type": "post",
                "caption": [
                    {
                        "node": {
                            "text": "ตร.แถลง น้ำที่ฉีดสลายชุมนุม 16 ตุลา\n\n-น้ำผสมสารเคมีประเภทสี ตั้งใจแยกแยะผู้ชุมนุม เพื่อดำเนินคดีในอนาคต ไม่มีอันตราย\n\n-สารเคมีผสมน้ำ ตั้งใจให้ชุมนุมยุติและล่าถอย จะส่งผลต่อผิวหนัง มีอาการแสบ ใช้น้ำล้างออกได้\n\n-ตร.ระบุว่าไม่ได้ใช้กระสุนยาง - แก๊สน้ำตา\n\n#ม็อบ16ตุลา #ไทยรัฐออนไลน์ #Thairath"
                        }
                    }
                ],
                "thumbnail_src": "https://instagram.fbkk2-8.fna.fbcdn.net/v/t51.2885-15/sh0.08/e35/s640x640/121500887_2680430278842021_5580307661557774015_n.jpg?_nc_ht=instagram.fbkk2-8.fna.fbcdn.net&_nc_cat=1&_nc_ohc=U40LhN82PzoAX9DHZW-&_nc_tp=24&oh=7dcfdcd7ddc705bd63327790d2775cdb&oe=5FB46248",
                "thumbnail_resources": [
                    {
                        "src": "https://instagram.fbkk2-8.fna.fbcdn.net/v/t51.2885-15/e35/s150x150/121500887_2680430278842021_5580307661557774015_n.jpg?_nc_ht=instagram.fbkk2-8.fna.fbcdn.net&_nc_cat=1&_nc_ohc=U40LhN82PzoAX9DHZW-&_nc_tp=15&oh=786447a8b974f8094d00ef0f59e4094d&oe=5FB48233",
                        "config_width": 150,
                        "config_height": 150
                    },
                    {
                        "src": "https://instagram.fbkk2-8.fna.fbcdn.net/v/t51.2885-15/e35/s240x240/121500887_2680430278842021_5580307661557774015_n.jpg?_nc_ht=instagram.fbkk2-8.fna.fbcdn.net&_nc_cat=1&_nc_ohc=U40LhN82PzoAX9DHZW-&_nc_tp=15&oh=a1397f548e66f7746f1be02822d6bc6a&oe=5FB42B7B",
                        "config_width": 240,
                        "config_height": 240
                    },
                    {
                        "src": "https://instagram.fbkk2-8.fna.fbcdn.net/v/t51.2885-15/e35/s320x320/121500887_2680430278842021_5580307661557774015_n.jpg?_nc_ht=instagram.fbkk2-8.fna.fbcdn.net&_nc_cat=1&_nc_ohc=U40LhN82PzoAX9DHZW-&_nc_tp=15&oh=74bf82b98e51aeb9b0a71c0c783e1681&oe=5FB39526",
                        "config_width": 320,
                        "config_height": 320
                    },
                    {
                        "src": "https://instagram.fbkk2-8.fna.fbcdn.net/v/t51.2885-15/e35/s480x480/121500887_2680430278842021_5580307661557774015_n.jpg?_nc_ht=instagram.fbkk2-8.fna.fbcdn.net&_nc_cat=1&_nc_ohc=U40LhN82PzoAX9DHZW-&_nc_tp=15&oh=f2be3774a1a6f07112860af5f337bcbb&oe=5FB4FC68",
                        "config_width": 480,
                        "config_height": 480
                    },
                    {
                        "src": "https://instagram.fbkk2-8.fna.fbcdn.net/v/t51.2885-15/sh0.08/e35/s640x640/121500887_2680430278842021_5580307661557774015_n.jpg?_nc_ht=instagram.fbkk2-8.fna.fbcdn.net&_nc_cat=1&_nc_ohc=U40LhN82PzoAX9DHZW-&_nc_tp=24&oh=7dcfdcd7ddc705bd63327790d2775cdb&oe=5FB46248",
                        "config_width": 640,
                        "config_height": 640
                    }
                ]
            },
            {
                "_id": "2421338777606949224",
                "display": "https://instagram.fbkk2-8.fna.fbcdn.net/v/t51.2885-15/e35/s1080x1080/121577638_1286247505060531_790121246064753173_n.jpg?_nc_ht=instagram.fbkk2-8.fna.fbcdn.net&_nc_cat=1&_nc_ohc=OpPbNhPq8DEAX_w9Dur&_nc_tp=15&oh=9c3a82326784aa13851b56f960c065c5&oe=5FB4AE5A",
                "type": "post",
                "caption": [
                    {
                        "node": {
                            "text": "16 ตุลาคม : \"ฟอร์ด\" ทัตเทพ เรืองประไพกิจเสรี เลขาธิการเยาวชนปลดแอก ถูกจับกุม ล่าสุดกำลังถูกนำตัวไป ตชด. ภาค 1\n\n#ม็อบ16ตุลา\n#ไทยรัฐออนไลน์"
                        }
                    }
                ],
                "thumbnail_src": "https://instagram.fbkk2-8.fna.fbcdn.net/v/t51.2885-15/sh0.08/e35/s640x640/121577638_1286247505060531_790121246064753173_n.jpg?_nc_ht=instagram.fbkk2-8.fna.fbcdn.net&_nc_cat=1&_nc_ohc=OpPbNhPq8DEAX_w9Dur&_nc_tp=24&oh=d57941274fdab4e12d3f0bb67b6fed6f&oe=5FB2A09E",
                "thumbnail_resources": [
                    {
                        "src": "https://instagram.fbkk2-8.fna.fbcdn.net/v/t51.2885-15/e35/s150x150/121577638_1286247505060531_790121246064753173_n.jpg?_nc_ht=instagram.fbkk2-8.fna.fbcdn.net&_nc_cat=1&_nc_ohc=OpPbNhPq8DEAX_w9Dur&_nc_tp=15&oh=338fac7c7790b6b1edc81fded7bf96f5&oe=5FB4E899",
                        "config_width": 150,
                        "config_height": 150
                    },
                    {
                        "src": "https://instagram.fbkk2-8.fna.fbcdn.net/v/t51.2885-15/e35/s240x240/121577638_1286247505060531_790121246064753173_n.jpg?_nc_ht=instagram.fbkk2-8.fna.fbcdn.net&_nc_cat=1&_nc_ohc=OpPbNhPq8DEAX_w9Dur&_nc_tp=15&oh=7c3be3de2cacf83f19aa69d4bc865712&oe=5FB4519F",
                        "config_width": 240,
                        "config_height": 240
                    },
                    {
                        "src": "https://instagram.fbkk2-8.fna.fbcdn.net/v/t51.2885-15/e35/s320x320/121577638_1286247505060531_790121246064753173_n.jpg?_nc_ht=instagram.fbkk2-8.fna.fbcdn.net&_nc_cat=1&_nc_ohc=OpPbNhPq8DEAX_w9Dur&_nc_tp=15&oh=453b626839c9f07609564a9d34f9cbe5&oe=5FB2D761",
                        "config_width": 320,
                        "config_height": 320
                    },
                    {
                        "src": "https://instagram.fbkk2-8.fna.fbcdn.net/v/t51.2885-15/e35/s480x480/121577638_1286247505060531_790121246064753173_n.jpg?_nc_ht=instagram.fbkk2-8.fna.fbcdn.net&_nc_cat=1&_nc_ohc=OpPbNhPq8DEAX_w9Dur&_nc_tp=15&oh=797822afd1e31a0f090afa17f316efdf&oe=5FB44A28",
                        "config_width": 480,
                        "config_height": 480
                    },
                    {
                        "src": "https://instagram.fbkk2-8.fna.fbcdn.net/v/t51.2885-15/sh0.08/e35/s640x640/121577638_1286247505060531_790121246064753173_n.jpg?_nc_ht=instagram.fbkk2-8.fna.fbcdn.net&_nc_cat=1&_nc_ohc=OpPbNhPq8DEAX_w9Dur&_nc_tp=24&oh=d57941274fdab4e12d3f0bb67b6fed6f&oe=5FB2A09E",
                        "config_width": 640,
                        "config_height": 640
                    }
                ]
            },
            {
                "_id": "2421281730642839432",
                "display": "https://instagram.fbkk2-8.fna.fbcdn.net/v/t51.2885-15/fr/e15/s1080x1080/121495578_202248257975828_190452969272095455_n.jpg?_nc_ht=instagram.fbkk2-8.fna.fbcdn.net&_nc_cat=1&_nc_ohc=1v4UG8rhsZ8AX-BR9-Z&oh=e33fa37bfbe99da21c35b942b2322d8f&oe=5FB5BE0A",
                "type": "post",
                "caption": [
                    {
                        "node": {
                            "text": "\"พิธา\" เจรจาตำรวจ งดฉีดน้ำใส่ผู้ชุมนุม ขอเข้าไปนำคนติดค้างแยกปทุมวันออก⁣\n⁣\n16 ตุลาคม : นายพิธา ลิ้มเจริญรัตน์ หัวหน้าพรรคก้าวไกล ใช้สิทธิ์ ส.ส. เจรจากับ ผบช.น. เพื่อขอเข้าไปด้านในแยกปทุมวัน นำตัวคนที่ติดอยู่ด้านในออกมา เนื่องจากตอนนี้คนที่อยู่ด้านในไม่สามารถกลับได้ เนื่องจากไม่มีรถ นอกจากนี้ยังขอเจ้าหน้าที่หยุดการฉีดน้ำใส่กลุ่มผู้ชุมนุม⁣\n⁣\n#พิธาลิ้มเจริญรัตน์ #ม็อบ16ตุลา #เกาะติดการชุมนุม63 #ไทยรัฐออนไลน์ #Thairath"
                        }
                    }
                ],
                "thumbnail_src": "https://instagram.fbkk2-8.fna.fbcdn.net/v/t51.2885-15/sh0.08/e35/s640x640/121495578_202248257975828_190452969272095455_n.jpg?_nc_ht=instagram.fbkk2-8.fna.fbcdn.net&_nc_cat=1&_nc_ohc=1v4UG8rhsZ8AX-BR9-Z&_nc_tp=24&oh=277fc2db2fb63b3856509d79d8d28994&oe=5FB56934",
                "thumbnail_resources": [
                    {
                        "src": "https://instagram.fbkk2-8.fna.fbcdn.net/v/t51.2885-15/e15/s150x150/121495578_202248257975828_190452969272095455_n.jpg?_nc_ht=instagram.fbkk2-8.fna.fbcdn.net&_nc_cat=1&_nc_ohc=1v4UG8rhsZ8AX-BR9-Z&_nc_tp=15&oh=08a0144b258d0b7a622bd45ca6d05f8e&oe=5FB2B4B6",
                        "config_width": 150,
                        "config_height": 150
                    },
                    {
                        "src": "https://instagram.fbkk2-8.fna.fbcdn.net/v/t51.2885-15/e15/s240x240/121495578_202248257975828_190452969272095455_n.jpg?_nc_ht=instagram.fbkk2-8.fna.fbcdn.net&_nc_cat=1&_nc_ohc=1v4UG8rhsZ8AX-BR9-Z&_nc_tp=15&oh=baaf9af5b33629d98bdb2fad5be28d2a&oe=5FB3ED00",
                        "config_width": 240,
                        "config_height": 240
                    },
                    {
                        "src": "https://instagram.fbkk2-8.fna.fbcdn.net/v/t51.2885-15/e15/s320x320/121495578_202248257975828_190452969272095455_n.jpg?_nc_ht=instagram.fbkk2-8.fna.fbcdn.net&_nc_cat=1&_nc_ohc=1v4UG8rhsZ8AX-BR9-Z&_nc_tp=15&oh=68f0c5ab26e375879e771d3af17d6803&oe=5FB5DA46",
                        "config_width": 320,
                        "config_height": 320
                    },
                    {
                        "src": "https://instagram.fbkk2-8.fna.fbcdn.net/v/t51.2885-15/e15/s480x480/121495578_202248257975828_190452969272095455_n.jpg?_nc_ht=instagram.fbkk2-8.fna.fbcdn.net&_nc_cat=1&_nc_ohc=1v4UG8rhsZ8AX-BR9-Z&_nc_tp=15&oh=8e4a78341f8c1fc3a82c78a5750a17d6&oe=5FB283A0",
                        "config_width": 480,
                        "config_height": 480
                    },
                    {
                        "src": "https://instagram.fbkk2-8.fna.fbcdn.net/v/t51.2885-15/sh0.08/e35/s640x640/121495578_202248257975828_190452969272095455_n.jpg?_nc_ht=instagram.fbkk2-8.fna.fbcdn.net&_nc_cat=1&_nc_ohc=1v4UG8rhsZ8AX-BR9-Z&_nc_tp=24&oh=277fc2db2fb63b3856509d79d8d28994&oe=5FB56934",
                        "config_width": 640,
                        "config_height": 640
                    }
                ]
            },
            {
                "_id": "2421279918014648945",
                "display": "https://instagram.fbkk2-8.fna.fbcdn.net/v/t51.2885-15/fr/e15/s1080x1080/121676021_446878526280975_6775015088241561067_n.jpg?_nc_ht=instagram.fbkk2-8.fna.fbcdn.net&_nc_cat=1&_nc_ohc=qqCyaQ2EnQUAX_rAyZQ&oh=238fc7d27fe59fabc670c0487a0ac644&oe=5FB5057D",
                "type": "post",
                "caption": [
                    {
                        "node": {
                            "text": "16 ตุลาคม : นายกฯ ประกาศต่อเวลาประกาศสถานการณ์ฉุกเฉินที่มีความร้ายแรงไปจนถึง 13 พ.ย. 63 (เฉพาะพื้นที่กรุงเทพ)⁣\n⁣\n#ม็อบ16ตุลา #ไทยรัฐออนไลน์ #Thairath"
                        }
                    }
                ],
                "thumbnail_src": "https://instagram.fbkk2-8.fna.fbcdn.net/v/t51.2885-15/sh0.08/e35/s640x640/121676021_446878526280975_6775015088241561067_n.jpg?_nc_ht=instagram.fbkk2-8.fna.fbcdn.net&_nc_cat=1&_nc_ohc=qqCyaQ2EnQUAX_rAyZQ&_nc_tp=24&oh=6f0527ab8a9d67bc7e78aa8fefca6a04&oe=5FB2ED36",
                "thumbnail_resources": [
                    {
                        "src": "https://instagram.fbkk2-8.fna.fbcdn.net/v/t51.2885-15/e15/s150x150/121676021_446878526280975_6775015088241561067_n.jpg?_nc_ht=instagram.fbkk2-8.fna.fbcdn.net&_nc_cat=1&_nc_ohc=qqCyaQ2EnQUAX_rAyZQ&_nc_tp=15&oh=8a72942352c7ce004db3d104f033da3e&oe=5FB4D189",
                        "config_width": 150,
                        "config_height": 150
                    },
                    {
                        "src": "https://instagram.fbkk2-8.fna.fbcdn.net/v/t51.2885-15/e15/s240x240/121676021_446878526280975_6775015088241561067_n.jpg?_nc_ht=instagram.fbkk2-8.fna.fbcdn.net&_nc_cat=1&_nc_ohc=qqCyaQ2EnQUAX_rAyZQ&_nc_tp=15&oh=c7a1fdeb7f11d8139d2cc5c414d14086&oe=5FB5148F",
                        "config_width": 240,
                        "config_height": 240
                    },
                    {
                        "src": "https://instagram.fbkk2-8.fna.fbcdn.net/v/t51.2885-15/e15/s320x320/121676021_446878526280975_6775015088241561067_n.jpg?_nc_ht=instagram.fbkk2-8.fna.fbcdn.net&_nc_cat=1&_nc_ohc=qqCyaQ2EnQUAX_rAyZQ&_nc_tp=15&oh=aa1f9bb3cde01415a7f4cf945a030357&oe=5FB5F671",
                        "config_width": 320,
                        "config_height": 320
                    },
                    {
                        "src": "https://instagram.fbkk2-8.fna.fbcdn.net/v/t51.2885-15/e15/s480x480/121676021_446878526280975_6775015088241561067_n.jpg?_nc_ht=instagram.fbkk2-8.fna.fbcdn.net&_nc_cat=1&_nc_ohc=qqCyaQ2EnQUAX_rAyZQ&_nc_tp=15&oh=3bb9a337f9bc9b33abe81c8c26240783&oe=5FB5E938",
                        "config_width": 480,
                        "config_height": 480
                    },
                    {
                        "src": "https://instagram.fbkk2-8.fna.fbcdn.net/v/t51.2885-15/sh0.08/e35/s640x640/121676021_446878526280975_6775015088241561067_n.jpg?_nc_ht=instagram.fbkk2-8.fna.fbcdn.net&_nc_cat=1&_nc_ohc=qqCyaQ2EnQUAX_rAyZQ&_nc_tp=24&oh=6f0527ab8a9d67bc7e78aa8fefca6a04&oe=5FB2ED36",
                        "config_width": 640,
                        "config_height": 640
                    }
                ]
            },
            {
                "_id": "2421276007238778769",
                "display": "https://instagram.fbkk2-8.fna.fbcdn.net/v/t51.2885-15/fr/e15/s1080x1080/121552141_218784949594205_8593966672895823320_n.jpg?_nc_ht=instagram.fbkk2-8.fna.fbcdn.net&_nc_cat=1&_nc_ohc=LA4sMaj8DnYAX8LMp3w&oh=296a4f665b29b621507e2a65b3f603c0&oe=5FB4E962",
                "type": "post",
                "caption": [
                    {
                        "node": {
                            "text": "20:50 น. สภาพความเสียหายบริเวณถนนพระราม1 ช่วงแยกเฉลิมเผ่าจนถึงแยกปทุมวัน หลังจากเกิดการปะทะระหว่างเจ้าหน้าที่ตำรวจกับกลุ่มผู้ชุมนุม เพื่อขอคืนพื้นที⁣\n⁣⁣\n⁣#ข่าวม็อบ #ม็อบ16ตุลา #เกาะติดการชุมนุม63 #ไทยรัฐออนไลน์ #Thairath"
                        }
                    }
                ],
                "thumbnail_src": "https://instagram.fbkk2-8.fna.fbcdn.net/v/t51.2885-15/e15/c180.0.719.719a/s640x640/121552141_218784949594205_8593966672895823320_n.jpg?_nc_ht=instagram.fbkk2-8.fna.fbcdn.net&_nc_cat=1&_nc_ohc=LA4sMaj8DnYAX8LMp3w&tp=16&oh=ad7daf7548d5f7119de95c3ec6e158e0&oe=5FB53618",
                "thumbnail_resources": [
                    {
                        "src": "https://instagram.fbkk2-8.fna.fbcdn.net/v/t51.2885-15/e15/c180.0.719.719a/s150x150/121552141_218784949594205_8593966672895823320_n.jpg?_nc_ht=instagram.fbkk2-8.fna.fbcdn.net&_nc_cat=1&_nc_ohc=LA4sMaj8DnYAX8LMp3w&tp=16&oh=a38466811913e12b2e090bb1dda6a803&oe=5FB398D5",
                        "config_width": 150,
                        "config_height": 150
                    },
                    {
                        "src": "https://instagram.fbkk2-8.fna.fbcdn.net/v/t51.2885-15/e15/c180.0.719.719a/s240x240/121552141_218784949594205_8593966672895823320_n.jpg?_nc_ht=instagram.fbkk2-8.fna.fbcdn.net&_nc_cat=1&_nc_ohc=LA4sMaj8DnYAX8LMp3w&tp=16&oh=08cbb494a61bd040db0b839a759985c9&oe=5FB2EFD3",
                        "config_width": 240,
                        "config_height": 240
                    },
                    {
                        "src": "https://instagram.fbkk2-8.fna.fbcdn.net/v/t51.2885-15/e15/c180.0.719.719a/s320x320/121552141_218784949594205_8593966672895823320_n.jpg?_nc_ht=instagram.fbkk2-8.fna.fbcdn.net&_nc_cat=1&_nc_ohc=LA4sMaj8DnYAX8LMp3w&tp=16&oh=476076f434f7543dacacbb6d2e33d0aa&oe=5FB42AAD",
                        "config_width": 320,
                        "config_height": 320
                    },
                    {
                        "src": "https://instagram.fbkk2-8.fna.fbcdn.net/v/t51.2885-15/e15/c180.0.719.719a/s480x480/121552141_218784949594205_8593966672895823320_n.jpg?_nc_ht=instagram.fbkk2-8.fna.fbcdn.net&_nc_cat=1&_nc_ohc=LA4sMaj8DnYAX8LMp3w&tp=16&oh=21407bc32f2fbb000e1310f6a7be823d&oe=5FB4086C",
                        "config_width": 480,
                        "config_height": 480
                    },
                    {
                        "src": "https://instagram.fbkk2-8.fna.fbcdn.net/v/t51.2885-15/e15/c180.0.719.719a/s640x640/121552141_218784949594205_8593966672895823320_n.jpg?_nc_ht=instagram.fbkk2-8.fna.fbcdn.net&_nc_cat=1&_nc_ohc=LA4sMaj8DnYAX8LMp3w&tp=16&oh=ad7daf7548d5f7119de95c3ec6e158e0&oe=5FB53618",
                        "config_width": 640,
                        "config_height": 640
                    }
                ]
            }
        ]
    },
    "newsIGTV": {
        "count": 885,
        "edges": [
            {
                "_id": "2420385224182771430",
                "display": "https://instagram.fbkk2-5.fna.fbcdn.net/v/t51.2885-15/e15/121606734_134026958430010_8289586485154459799_n.jpg?_nc_ht=instagram.fbkk2-5.fna.fbcdn.net&_nc_cat=110&_nc_ohc=JEvbKEDFfK0AX8eyilt&_nc_tp=18&oh=a76ae785b061831f29c76156ab69991f&oe=5F8C982C",
                "title": "Siri มงคล Ep.2 ดูดวงการเงินกับหมอไก่ พ.พาทินี",
                "type": "igtv",
                "caption": [
                    {
                        "node": {
                            "text": "สุดปังปุริเย่ 3 ราศีการเงินเด่นสุดๆ หลังพระราหูย้าย มีโชค มีเงิน ร่ำรวย ทุกโซเชียลมีเดีย ไทยรัฐออนไลน์ ที่เดียว\n@morkai_thairath\n\n#ดูดวงการเงิน #12ราศี #ราศี #ความเชื่อ #ดูดวง #ดูดวงไทยรัฐ #หมอไก่"
                        }
                    }
                ],
                "thumbnail_src": "https://instagram.fbkk2-5.fna.fbcdn.net/v/t51.2885-15/e15/c0.280.720.720a/s640x640/121606734_134026958430010_8289586485154459799_n.jpg?_nc_ht=instagram.fbkk2-5.fna.fbcdn.net&_nc_cat=110&_nc_ohc=JEvbKEDFfK0AX8eyilt&tp=16&oh=c7ee22c8e505579c489798bfebbf0bbe&oe=5F8D206F",
                "thumbnail_resources": [
                    {
                        "src": "https://instagram.fbkk2-5.fna.fbcdn.net/v/t51.2885-15/e15/p150x150/121606734_134026958430010_8289586485154459799_n.jpg?_nc_ht=instagram.fbkk2-5.fna.fbcdn.net&_nc_cat=110&_nc_ohc=JEvbKEDFfK0AX8eyilt&tp=19&oh=46b17b1dc68ff9bad8adb46409537cbd&oe=5F8CCD51",
                        "config_width": 150,
                        "config_height": 266
                    },
                    {
                        "src": "https://instagram.fbkk2-5.fna.fbcdn.net/v/t51.2885-15/e15/p240x240/121606734_134026958430010_8289586485154459799_n.jpg?_nc_ht=instagram.fbkk2-5.fna.fbcdn.net&_nc_cat=110&_nc_ohc=JEvbKEDFfK0AX8eyilt&tp=19&oh=5a4e5d5249870967b2e8988c092ce0c7&oe=5F8C8857",
                        "config_width": 240,
                        "config_height": 426
                    },
                    {
                        "src": "https://instagram.fbkk2-5.fna.fbcdn.net/v/t51.2885-15/e15/p320x320/121606734_134026958430010_8289586485154459799_n.jpg?_nc_ht=instagram.fbkk2-5.fna.fbcdn.net&_nc_cat=110&_nc_ohc=JEvbKEDFfK0AX8eyilt&tp=19&oh=885d18ff6ddf8bad08dea2a722f56106&oe=5F8CB529",
                        "config_width": 320,
                        "config_height": 568
                    },
                    {
                        "src": "https://instagram.fbkk2-5.fna.fbcdn.net/v/t51.2885-15/e15/p480x480/121606734_134026958430010_8289586485154459799_n.jpg?_nc_ht=instagram.fbkk2-5.fna.fbcdn.net&_nc_cat=110&_nc_ohc=JEvbKEDFfK0AX8eyilt&tp=19&oh=ec469a504c5fe2a0c17ce3ebbe91d11c&oe=5F8CEE30",
                        "config_width": 480,
                        "config_height": 853
                    },
                    {
                        "src": "https://instagram.fbkk2-5.fna.fbcdn.net/v/t51.2885-15/e15/p640x640/121606734_134026958430010_8289586485154459799_n.jpg?_nc_ht=instagram.fbkk2-5.fna.fbcdn.net&_nc_cat=110&_nc_ohc=JEvbKEDFfK0AX8eyilt&tp=19&oh=046f80c6fb025afae048d34ca7e04469&oe=5F8CD714",
                        "config_width": 640,
                        "config_height": 1137
                    }
                ]
            },
            {
                "_id": "2418271510319211460",
                "display": "https://instagram.fbkk2-4.fna.fbcdn.net/v/t51.2885-15/e15/120926374_362342861577229_1046770517645902904_n.jpg?_nc_ht=instagram.fbkk2-4.fna.fbcdn.net&_nc_cat=101&_nc_ohc=0fZMl2Sr2l0AX9t7lgH&_nc_tp=18&oh=437662d64fa03c38a78d0e8415dbeb8c&oe=5F8CBBB3",
                "title": "Thairath Talk หนุ่ม กรรชัย บอกชื่อจริงไม่ใช่ กรรชัย",
                "type": "igtv",
                "caption": [
                    {
                        "node": {
                            "text": "เรื่องเล่าสุดฮา แท้จริง ‘หนุ่ม กรรชัย กำเนิดพลอย’ ไม่ได้ชื่อ ‘กรรชัย’ จะชื่อว่าอะไร ต้องชม!\n@kanchai\n\n#เบอร์ใหญ่ต้องThairathTalk #ThairathTalk #ไทยรัฐทอล์ก #ThairathTalk2020 #หนุ่มกรรชัย #กรรชัยกำเนิดพลอย \n#ข่าวช่อง3 #โหนกระแส"
                        }
                    }
                ],
                "thumbnail_src": "https://instagram.fbkk2-4.fna.fbcdn.net/v/t51.2885-15/e15/c0.280.720.720a/s640x640/120926374_362342861577229_1046770517645902904_n.jpg?_nc_ht=instagram.fbkk2-4.fna.fbcdn.net&_nc_cat=101&_nc_ohc=0fZMl2Sr2l0AX9t7lgH&tp=16&oh=b27000ff2f442b356848eb29007bfacd&oe=5F8CE6F8",
                "thumbnail_resources": [
                    {
                        "src": "https://instagram.fbkk2-4.fna.fbcdn.net/v/t51.2885-15/e15/p150x150/120926374_362342861577229_1046770517645902904_n.jpg?_nc_ht=instagram.fbkk2-4.fna.fbcdn.net&_nc_cat=101&_nc_ohc=0fZMl2Sr2l0AX9t7lgH&tp=19&oh=6d581aa0459342a7b4dfd1aff6cdaed2&oe=5F8CF10A",
                        "config_width": 150,
                        "config_height": 266
                    },
                    {
                        "src": "https://instagram.fbkk2-4.fna.fbcdn.net/v/t51.2885-15/e15/p240x240/120926374_362342861577229_1046770517645902904_n.jpg?_nc_ht=instagram.fbkk2-4.fna.fbcdn.net&_nc_cat=101&_nc_ohc=0fZMl2Sr2l0AX9t7lgH&tp=19&oh=f4f465a22ec8009a47fb682ad20f77bc&oe=5F8CCF50",
                        "config_width": 240,
                        "config_height": 426
                    },
                    {
                        "src": "https://instagram.fbkk2-4.fna.fbcdn.net/v/t51.2885-15/e15/p320x320/120926374_362342861577229_1046770517645902904_n.jpg?_nc_ht=instagram.fbkk2-4.fna.fbcdn.net&_nc_cat=101&_nc_ohc=0fZMl2Sr2l0AX9t7lgH&tp=19&oh=dac2a090f0eba6caa900d1e14ed290b7&oe=5F8C9C32",
                        "config_width": 320,
                        "config_height": 568
                    },
                    {
                        "src": "https://instagram.fbkk2-4.fna.fbcdn.net/v/t51.2885-15/e15/p480x480/120926374_362342861577229_1046770517645902904_n.jpg?_nc_ht=instagram.fbkk2-4.fna.fbcdn.net&_nc_cat=101&_nc_ohc=0fZMl2Sr2l0AX9t7lgH&tp=19&oh=ac9e1899b19beea36e61f1fec5813159&oe=5F8CEFB7",
                        "config_width": 480,
                        "config_height": 853
                    },
                    {
                        "src": "https://instagram.fbkk2-4.fna.fbcdn.net/v/t51.2885-15/e15/p640x640/120926374_362342861577229_1046770517645902904_n.jpg?_nc_ht=instagram.fbkk2-4.fna.fbcdn.net&_nc_cat=101&_nc_ohc=0fZMl2Sr2l0AX9t7lgH&tp=19&oh=5486f0c6c741cd97d37af311926c1962&oe=5F8CA84B",
                        "config_width": 640,
                        "config_height": 1137
                    }
                ]
            },
            {
                "_id": "2418090290373244554",
                "display": "https://instagram.fbkk2-4.fna.fbcdn.net/v/t51.2885-15/fr/e15/p1080x1080/120842626_189078842674825_401501247769613536_n.jpg?_nc_ht=instagram.fbkk2-4.fna.fbcdn.net&_nc_cat=101&_nc_ohc=33-SrDBoebUAX-xHhgJ&oh=7d814fbe8a9ef89c8a425612677c291a&oe=5F8CF49F",
                "title": "รำลึก โจ้ นิสา วงศ์วัฒน์",
                "type": "igtv",
                "caption": [
                    {
                        "node": {
                            "text": "25 ปี อุบัติเหตุโค้งร้อยศพ คร่า “นิสา วงศ์วัฒน์” นางเอกยอดกตัญญู ที่เริ่มต้นชีวิตนักแสดงจากหนังบู๊ก่อนเข้าสู่วงการละคร #3นาทีคดีดัง \n\n#ไทยรัฐออนไลน์"
                        }
                    }
                ],
                "thumbnail_src": "https://instagram.fbkk2-4.fna.fbcdn.net/v/t51.2885-15/sh0.08/e35/c0.420.1080.1080a/s640x640/120842626_189078842674825_401501247769613536_n.jpg?_nc_ht=instagram.fbkk2-4.fna.fbcdn.net&_nc_cat=101&_nc_ohc=33-SrDBoebUAX-xHhgJ&oh=a3fada8e047df88a1b7bf6ed0a6c9200&oe=5F8CCE31",
                "thumbnail_resources": [
                    {
                        "src": "https://instagram.fbkk2-4.fna.fbcdn.net/v/t51.2885-15/e15/p150x150/120842626_189078842674825_401501247769613536_n.jpg?_nc_ht=instagram.fbkk2-4.fna.fbcdn.net&_nc_cat=101&_nc_ohc=33-SrDBoebUAX-xHhgJ&tp=19&oh=a7bc3dbdb2749dfdf3db32c3737c4bcf&oe=5F8D06B1",
                        "config_width": 150,
                        "config_height": 266
                    },
                    {
                        "src": "https://instagram.fbkk2-4.fna.fbcdn.net/v/t51.2885-15/e15/p240x240/120842626_189078842674825_401501247769613536_n.jpg?_nc_ht=instagram.fbkk2-4.fna.fbcdn.net&_nc_cat=101&_nc_ohc=33-SrDBoebUAX-xHhgJ&tp=19&oh=68d3526d463c013b72e258b8fa0139ae&oe=5F8D153B",
                        "config_width": 240,
                        "config_height": 426
                    },
                    {
                        "src": "https://instagram.fbkk2-4.fna.fbcdn.net/v/t51.2885-15/e15/p320x320/120842626_189078842674825_401501247769613536_n.jpg?_nc_ht=instagram.fbkk2-4.fna.fbcdn.net&_nc_cat=101&_nc_ohc=33-SrDBoebUAX-xHhgJ&tp=19&oh=d98fef6aceb841d3f751ad264ed9711d&oe=5F8C8B41",
                        "config_width": 320,
                        "config_height": 568
                    },
                    {
                        "src": "https://instagram.fbkk2-4.fna.fbcdn.net/v/t51.2885-15/e15/p480x480/120842626_189078842674825_401501247769613536_n.jpg?_nc_ht=instagram.fbkk2-4.fna.fbcdn.net&_nc_cat=101&_nc_ohc=33-SrDBoebUAX-xHhgJ&tp=19&oh=6313f6e1eb58811197e51fad72962450&oe=5F8D2BDB",
                        "config_width": 480,
                        "config_height": 853
                    },
                    {
                        "src": "https://instagram.fbkk2-4.fna.fbcdn.net/v/t51.2885-15/sh0.08/e35/p640x640/120842626_189078842674825_401501247769613536_n.jpg?_nc_ht=instagram.fbkk2-4.fna.fbcdn.net&_nc_cat=101&_nc_ohc=33-SrDBoebUAX-xHhgJ&_nc_tp=25&oh=6823f55858dfc846dd44d643af0b08fb&oe=5F8CCB37",
                        "config_width": 640,
                        "config_height": 1137
                    }
                ]
            },
            {
                "_id": "2417365027096712090",
                "display": "https://instagram.fbkk2-7.fna.fbcdn.net/v/t51.2885-15/e15/121139985_346846093315134_1886201609785135046_n.jpg?_nc_ht=instagram.fbkk2-7.fna.fbcdn.net&_nc_cat=106&_nc_ohc=Ew3rPlChxuIAX-3xREu&_nc_tp=18&oh=3650edb4b39a0dbb8d1ccf1a670b39fa&oe=5F8C9DB4",
                "title": "\"ห้าง-ค้าปลีก\" ยังไม่ฟื้น",
                "type": "igtv",
                "caption": [
                    {
                        "node": {
                            "text": "หาคำตอบ...ทำไมวัยรุ่นช็อปปิงห้างน้อยลง ยอดขายในอเมริกาแตะสุดต่ำสุดในรอบ 2 ทศวรรษ แม้ตลาดอีคอมเมิร์ซพุ่งแรง แต่ \"ธุรกิจค้าปลีก\" ยังไม่ฟื้น... BIG NAMES, BIG PAINS\n\n#ไทยรัฐออนไลน์"
                        }
                    }
                ],
                "thumbnail_src": "https://instagram.fbkk2-7.fna.fbcdn.net/v/t51.2885-15/e15/c0.280.720.720a/s640x640/121139985_346846093315134_1886201609785135046_n.jpg?_nc_ht=instagram.fbkk2-7.fna.fbcdn.net&_nc_cat=106&_nc_ohc=Ew3rPlChxuIAX-3xREu&tp=16&oh=99cee73171cf7a5e5ca7ae7f6a3de196&oe=5F8CDAF7",
                "thumbnail_resources": [
                    {
                        "src": "https://instagram.fbkk2-7.fna.fbcdn.net/v/t51.2885-15/e15/p150x150/121139985_346846093315134_1886201609785135046_n.jpg?_nc_ht=instagram.fbkk2-7.fna.fbcdn.net&_nc_cat=106&_nc_ohc=Ew3rPlChxuIAX-3xREu&tp=19&oh=c29cfea5f2b3e7598f36ea91daff236f&oe=5F8CCFC9",
                        "config_width": 150,
                        "config_height": 266
                    },
                    {
                        "src": "https://instagram.fbkk2-7.fna.fbcdn.net/v/t51.2885-15/e15/p240x240/121139985_346846093315134_1886201609785135046_n.jpg?_nc_ht=instagram.fbkk2-7.fna.fbcdn.net&_nc_cat=106&_nc_ohc=Ew3rPlChxuIAX-3xREu&tp=19&oh=6f36eebff3803803cac54d3528a55a3a&oe=5F8CC7CF",
                        "config_width": 240,
                        "config_height": 426
                    },
                    {
                        "src": "https://instagram.fbkk2-7.fna.fbcdn.net/v/t51.2885-15/e15/p320x320/121139985_346846093315134_1886201609785135046_n.jpg?_nc_ht=instagram.fbkk2-7.fna.fbcdn.net&_nc_cat=106&_nc_ohc=Ew3rPlChxuIAX-3xREu&tp=19&oh=7fe4f659f405e692a568bdf8efe31d7c&oe=5F8CD831",
                        "config_width": 320,
                        "config_height": 568
                    },
                    {
                        "src": "https://instagram.fbkk2-7.fna.fbcdn.net/v/t51.2885-15/e15/p480x480/121139985_346846093315134_1886201609785135046_n.jpg?_nc_ht=instagram.fbkk2-7.fna.fbcdn.net&_nc_cat=106&_nc_ohc=Ew3rPlChxuIAX-3xREu&tp=19&oh=21c589e51bd48a6bc92d65edadacb899&oe=5F8C9FB8",
                        "config_width": 480,
                        "config_height": 853
                    },
                    {
                        "src": "https://instagram.fbkk2-7.fna.fbcdn.net/v/t51.2885-15/e15/p640x640/121139985_346846093315134_1886201609785135046_n.jpg?_nc_ht=instagram.fbkk2-7.fna.fbcdn.net&_nc_cat=106&_nc_ohc=Ew3rPlChxuIAX-3xREu&tp=19&oh=5dd463d308974e7e904ddb9905172c46&oe=5F8CC64C",
                        "config_width": 640,
                        "config_height": 1137
                    }
                ]
            },
            {
                "_id": "2415595985266036934",
                "display": "https://instagram.fbkk2-6.fna.fbcdn.net/v/t51.2885-15/e35/p1080x1080/120973706_714401705841283_2910023954335017701_n.jpg?_nc_ht=instagram.fbkk2-6.fna.fbcdn.net&_nc_cat=107&_nc_ohc=hk8d9dTUOpAAX-PkMmL&tp=19&oh=7d6cbfff42c2dc5b7f2399e30b6b3d21&oe=5F8CD30C",
                "title": "#ไฟไหม้ ลามทั้งตึก 33 ชั้น เกาหลีใต้",
                "type": "igtv",
                "caption": [
                    {
                        "node": {
                            "text": ".\nเพลิงไหม้รุนแรง ตึกอพาร์ตเมนต์สูง 33 ชั้น เมือง #อุลซาน ประเทศ #เกาหลีใต้ เมื่อ 23.07 น. ของวันที่ 8 ตุลาคม ตามเวลาท้องถิ่น ไฟเริ่มไหม้ที่ชั้น 12 ของอาคาร จากนั้นลมพัดลุกลามไปทั่วทั้งตึก\n\n#ไทยรัฐออนไลน์ #Thairath"
                        }
                    }
                ],
                "thumbnail_src": "https://instagram.fbkk2-6.fna.fbcdn.net/v/t51.2885-15/sh0.08/e35/c0.1194.3072.3072a/s640x640/120973706_714401705841283_2910023954335017701_n.jpg?_nc_ht=instagram.fbkk2-6.fna.fbcdn.net&_nc_cat=107&_nc_ohc=hk8d9dTUOpAAX-PkMmL&oh=9ec960db4da9e81b8db5788907cc1f23&oe=5F8C84E1",
                "thumbnail_resources": [
                    {
                        "src": "https://instagram.fbkk2-6.fna.fbcdn.net/v/t51.2885-15/e35/p150x150/120973706_714401705841283_2910023954335017701_n.jpg?_nc_ht=instagram.fbkk2-6.fna.fbcdn.net&_nc_cat=107&_nc_ohc=hk8d9dTUOpAAX-PkMmL&tp=19&oh=e7dc261311fef29bcbefae2c499de47e&oe=5F8CA40C",
                        "config_width": 150,
                        "config_height": 266
                    },
                    {
                        "src": "https://instagram.fbkk2-6.fna.fbcdn.net/v/t51.2885-15/e35/p240x240/120973706_714401705841283_2910023954335017701_n.jpg?_nc_ht=instagram.fbkk2-6.fna.fbcdn.net&_nc_cat=107&_nc_ohc=hk8d9dTUOpAAX-PkMmL&tp=19&oh=b798eedcfcc8b2fb9838dfd2d492f83f&oe=5F8D2A8E",
                        "config_width": 240,
                        "config_height": 426
                    },
                    {
                        "src": "https://instagram.fbkk2-6.fna.fbcdn.net/v/t51.2885-15/e35/p320x320/120973706_714401705841283_2910023954335017701_n.jpg?_nc_ht=instagram.fbkk2-6.fna.fbcdn.net&_nc_cat=107&_nc_ohc=hk8d9dTUOpAAX-PkMmL&tp=19&oh=8d869745fa228a6143e3cf114e2b034b&oe=5F8D0134",
                        "config_width": 320,
                        "config_height": 568
                    },
                    {
                        "src": "https://instagram.fbkk2-6.fna.fbcdn.net/v/t51.2885-15/e35/p480x480/120973706_714401705841283_2910023954335017701_n.jpg?_nc_ht=instagram.fbkk2-6.fna.fbcdn.net&_nc_cat=107&_nc_ohc=hk8d9dTUOpAAX-PkMmL&tp=19&oh=c12c7f6f150472ba217e9aa664e650d0&oe=5F8C90F5",
                        "config_width": 480,
                        "config_height": 853
                    },
                    {
                        "src": "https://instagram.fbkk2-6.fna.fbcdn.net/v/t51.2885-15/sh0.08/e35/p640x640/120973706_714401705841283_2910023954335017701_n.jpg?_nc_ht=instagram.fbkk2-6.fna.fbcdn.net&_nc_cat=107&_nc_ohc=hk8d9dTUOpAAX-PkMmL&_nc_tp=25&oh=c2878cd1218557e5c44c219a4c24bd02&oe=5F8CD04F",
                        "config_width": 640,
                        "config_height": 1137
                    }
                ]
            },
            {
                "_id": "2415377460114120116",
                "display": "https://instagram.fbkk2-4.fna.fbcdn.net/v/t51.2885-15/e15/120815882_349870292734193_4405991926892435281_n.jpg?_nc_ht=instagram.fbkk2-4.fna.fbcdn.net&_nc_cat=105&_nc_ohc=_Y8r-X9SyxUAX-IXQpN&_nc_tp=18&oh=c653b40bc56fd4a99e40009ad65b5396&oe=5F8CF6F2",
                "title": "Thairath Talk หนุ่ม กรรชัย ฆ่าข่มขืนควรประหาร",
                "type": "igtv",
                "caption": [
                    {
                        "node": {
                            "text": "หนุ่ม กรรชัย จากหัวอกคนมีลูกผู้หญิง ฆ่าข่มขืนควรประหารไปเลย \n\n‘วันนี้ความเลวทรามระยำตำบอนไปถึงขั้นที่ครูข่มขืนเด็กนักเรียน สุดท้ายให้พักราชการไว้ก่อน พักทำไม จะให้ออกก็ออกไปเลย แต่คำเหล่านี้ไม่สามารถพูดในตอนที่อ่านข่าว แต่ในความรู้สึกของพี่มันเรียกร้องอยู่ข้างใน เพราะพี่เป็นมนุษย์มีลูกผู้หญิง พี่แค่รู้สึกแบบนี้’\n@kanchai\n\n#เบอร์ใหญ่ต้องThairathTalk #ThairathTalk #ไทยรัฐทอล์ก #ThairathTalk2020 #หนุ่มกรรชัย #กรรชัยกำเนิดพลอย \n#ข่าวช่อง3 #โหนกระแส"
                        }
                    }
                ],
                "thumbnail_src": "https://instagram.fbkk2-4.fna.fbcdn.net/v/t51.2885-15/e15/c0.280.720.720a/s640x640/120815882_349870292734193_4405991926892435281_n.jpg?_nc_ht=instagram.fbkk2-4.fna.fbcdn.net&_nc_cat=105&_nc_ohc=_Y8r-X9SyxUAX-IXQpN&tp=16&oh=256d42b0033172b4445f877c79c725ee&oe=5F8D1F75",
                "thumbnail_resources": [
                    {
                        "src": "https://instagram.fbkk2-4.fna.fbcdn.net/v/t51.2885-15/e15/p150x150/120815882_349870292734193_4405991926892435281_n.jpg?_nc_ht=instagram.fbkk2-4.fna.fbcdn.net&_nc_cat=105&_nc_ohc=_Y8r-X9SyxUAX-IXQpN&tp=19&oh=24d90d8660807ac40a94aaa63732e02c&oe=5F8CDE4B",
                        "config_width": 150,
                        "config_height": 266
                    },
                    {
                        "src": "https://instagram.fbkk2-4.fna.fbcdn.net/v/t51.2885-15/e15/p240x240/120815882_349870292734193_4405991926892435281_n.jpg?_nc_ht=instagram.fbkk2-4.fna.fbcdn.net&_nc_cat=105&_nc_ohc=_Y8r-X9SyxUAX-IXQpN&tp=19&oh=8e2beafad58acd92a60e69c5438795ad&oe=5F8C8BCD",
                        "config_width": 240,
                        "config_height": 426
                    },
                    {
                        "src": "https://instagram.fbkk2-4.fna.fbcdn.net/v/t51.2885-15/e15/p320x320/120815882_349870292734193_4405991926892435281_n.jpg?_nc_ht=instagram.fbkk2-4.fna.fbcdn.net&_nc_cat=105&_nc_ohc=_Y8r-X9SyxUAX-IXQpN&tp=19&oh=7b024d5beed4bb2a628d15eea4e9a18d&oe=5F8CC633",
                        "config_width": 320,
                        "config_height": 568
                    },
                    {
                        "src": "https://instagram.fbkk2-4.fna.fbcdn.net/v/t51.2885-15/e15/p480x480/120815882_349870292734193_4405991926892435281_n.jpg?_nc_ht=instagram.fbkk2-4.fna.fbcdn.net&_nc_cat=105&_nc_ohc=_Y8r-X9SyxUAX-IXQpN&tp=19&oh=b177f5d1b02c0e8e761310d57d3d41b4&oe=5F8C93B6",
                        "config_width": 480,
                        "config_height": 853
                    },
                    {
                        "src": "https://instagram.fbkk2-4.fna.fbcdn.net/v/t51.2885-15/e15/p640x640/120815882_349870292734193_4405991926892435281_n.jpg?_nc_ht=instagram.fbkk2-4.fna.fbcdn.net&_nc_cat=105&_nc_ohc=_Y8r-X9SyxUAX-IXQpN&tp=19&oh=da41154c82b401518594bb2ccc87906e&oe=5F8CB38A",
                        "config_width": 640,
                        "config_height": 1137
                    }
                ]
            },
            {
                "_id": "2415314492251483596",
                "display": "https://instagram.fbkk2-6.fna.fbcdn.net/v/t51.2885-15/e15/120999207_353932605660823_4152863946387472331_n.jpg?_nc_ht=instagram.fbkk2-6.fna.fbcdn.net&_nc_cat=107&_nc_ohc=8XohqVwWHVIAX_rSu-F&_nc_tp=18&oh=52c30b0d8fc24f8b8e8ce9de316c94f6&oe=5F8CF9A8",
                "title": "สีรถมงคล 2563",
                "type": "igtv",
                "caption": [
                    {
                        "node": {
                            "text": "ประเดิมวันแรก สิริมงคล 2020 ที่เอาหมอดูชื่อดัง การันตีความแม่นยำ น่าเชื่อถือจาก ‘ไทยรัฐออนไลน์’ มาสร้างคอนเทนต์เพื่อเป็นไกด์ไลน์ดวงเน้นฮาวทูสบายๆ ให้กับผู้ชม \n\nสิริมงคล 2020 ประเดิมถามหมอมีน อาจารย์ อรรถพล น้อยวงศ์ หมอดูชื่อดังถามไถ่เรื่องความเชื่อ เรื่องสีรถมงคล ขับแล้วเฮง สงบ ปลอดภัย สีไหนรับทรัพย์ การงาน ปังๆ ทุกโซเชียลมีเดียของไทยรัฐออนไลน์ น่ารัก สนุก แค่ไหน ไปชมกัน\n@mastermeenforyou \n\n#สีรถมงคล\n#ความเชื่อ\n#ดูดวง\n#ดูดวงไทยรัฐ\n#หมอมีน"
                        }
                    }
                ],
                "thumbnail_src": "https://instagram.fbkk2-6.fna.fbcdn.net/v/t51.2885-15/e15/c0.280.720.720a/s640x640/120999207_353932605660823_4152863946387472331_n.jpg?_nc_ht=instagram.fbkk2-6.fna.fbcdn.net&_nc_cat=107&_nc_ohc=8XohqVwWHVIAX_rSu-F&tp=16&oh=52770f18c5867e58dfa2fbfceabb79c6&oe=5F8CD063",
                "thumbnail_resources": [
                    {
                        "src": "https://instagram.fbkk2-6.fna.fbcdn.net/v/t51.2885-15/e15/p150x150/120999207_353932605660823_4152863946387472331_n.jpg?_nc_ht=instagram.fbkk2-6.fna.fbcdn.net&_nc_cat=107&_nc_ohc=8XohqVwWHVIAX_rSu-F&tp=19&oh=bb5950363f8e8c579d30cd1f06f952a5&oe=5F8CB6DD",
                        "config_width": 150,
                        "config_height": 266
                    },
                    {
                        "src": "https://instagram.fbkk2-6.fna.fbcdn.net/v/t51.2885-15/e15/p240x240/120999207_353932605660823_4152863946387472331_n.jpg?_nc_ht=instagram.fbkk2-6.fna.fbcdn.net&_nc_cat=107&_nc_ohc=8XohqVwWHVIAX_rSu-F&tp=19&oh=1fabed759a7d137119d2f5c4e3cc325c&oe=5F8CBF1B",
                        "config_width": 240,
                        "config_height": 426
                    },
                    {
                        "src": "https://instagram.fbkk2-6.fna.fbcdn.net/v/t51.2885-15/e15/p320x320/120999207_353932605660823_4152863946387472331_n.jpg?_nc_ht=instagram.fbkk2-6.fna.fbcdn.net&_nc_cat=107&_nc_ohc=8XohqVwWHVIAX_rSu-F&tp=19&oh=f3aae88a47a3ec02dc95e6d549d23b05&oe=5F8CCBE5",
                        "config_width": 320,
                        "config_height": 568
                    },
                    {
                        "src": "https://instagram.fbkk2-6.fna.fbcdn.net/v/t51.2885-15/e15/p480x480/120999207_353932605660823_4152863946387472331_n.jpg?_nc_ht=instagram.fbkk2-6.fna.fbcdn.net&_nc_cat=107&_nc_ohc=8XohqVwWHVIAX_rSu-F&tp=19&oh=8ef6c118bf1fd26872a5b0ef6f5b16c0&oe=5F8D01E4",
                        "config_width": 480,
                        "config_height": 853
                    },
                    {
                        "src": "https://instagram.fbkk2-6.fna.fbcdn.net/v/t51.2885-15/e15/p640x640/120999207_353932605660823_4152863946387472331_n.jpg?_nc_ht=instagram.fbkk2-6.fna.fbcdn.net&_nc_cat=107&_nc_ohc=8XohqVwWHVIAX_rSu-F&tp=19&oh=ac629c0f606901e5123cc64757fa7760&oe=5F8CA760",
                        "config_width": 640,
                        "config_height": 1137
                    }
                ]
            },
            {
                "_id": "2413922616849771987",
                "display": "https://instagram.fbkk2-4.fna.fbcdn.net/v/t51.2885-15/e15/120898202_2854648384746569_8282414046894556517_n.jpg?_nc_ht=instagram.fbkk2-4.fna.fbcdn.net&_nc_cat=105&_nc_ohc=2ovs9AVeXPcAX8d3PY8&_nc_tp=18&oh=f315b2ea33108568bfd371a68aaadb65&oe=5F8D0150",
                "title": "Thairath Talk คุย 51 ปี หนุ่ม กรรชัย ชีวิต แผลในใจ ที่แรก",
                "type": "igtv",
                "caption": [
                    {
                        "node": {
                            "text": "เมื่อพิธีกรจอมขยี้ปะทะพิธีกร Thairath Talk นักขยี้ขออนุญาตคุ้ยแผลในใจ โดนด่าสื่อเทียม 'สื่อเป็นสื่อกลางได้ เป็นคนกลางไม่ได้ ถ้าพูดต่อหน้าผมจะยกนิ้วกลางให้’\n\nเรื่องลับส่วนตัวที่สนุก ฮา ชนิดไม่เคยฟัง\n@kanchai \n\n#เบอร์ใหญ่ต้องThairathTalk #ThairathTalk #ไทยรัฐทอล์ก #ThairathTalk2020 #หนุ่มกรรชัย #กรรชัยกำเนิดพลอย #ไมค์ซาร่า \n#ศรรามติ๊ก\n#ข่าวช่อง3 #โหนกระแส"
                        }
                    }
                ],
                "thumbnail_src": "https://instagram.fbkk2-4.fna.fbcdn.net/v/t51.2885-15/e15/c0.280.720.720a/s640x640/120898202_2854648384746569_8282414046894556517_n.jpg?_nc_ht=instagram.fbkk2-4.fna.fbcdn.net&_nc_cat=105&_nc_ohc=2ovs9AVeXPcAX8d3PY8&tp=16&oh=3915d976384ed5406e0c4b4d049956a1&oe=5F8D0D9B",
                "thumbnail_resources": [
                    {
                        "src": "https://instagram.fbkk2-4.fna.fbcdn.net/v/t51.2885-15/e15/p150x150/120898202_2854648384746569_8282414046894556517_n.jpg?_nc_ht=instagram.fbkk2-4.fna.fbcdn.net&_nc_cat=105&_nc_ohc=2ovs9AVeXPcAX8d3PY8&tp=19&oh=8ac9b1f210be9f0630e73d2ec1fa23d0&oe=5F8CDC2A",
                        "config_width": 150,
                        "config_height": 266
                    },
                    {
                        "src": "https://instagram.fbkk2-4.fna.fbcdn.net/v/t51.2885-15/e15/p240x240/120898202_2854648384746569_8282414046894556517_n.jpg?_nc_ht=instagram.fbkk2-4.fna.fbcdn.net&_nc_cat=105&_nc_ohc=2ovs9AVeXPcAX8d3PY8&tp=19&oh=bbbf9a56bc69ab71c47652cc02dde74b&oe=5F8C8662",
                        "config_width": 240,
                        "config_height": 426
                    },
                    {
                        "src": "https://instagram.fbkk2-4.fna.fbcdn.net/v/t51.2885-15/e15/p320x320/120898202_2854648384746569_8282414046894556517_n.jpg?_nc_ht=instagram.fbkk2-4.fna.fbcdn.net&_nc_cat=105&_nc_ohc=2ovs9AVeXPcAX8d3PY8&tp=19&oh=4135b59cd96e7d18c8abd5edf18ca29c&oe=5F8CF33F",
                        "config_width": 320,
                        "config_height": 568
                    },
                    {
                        "src": "https://instagram.fbkk2-4.fna.fbcdn.net/v/t51.2885-15/e15/p480x480/120898202_2854648384746569_8282414046894556517_n.jpg?_nc_ht=instagram.fbkk2-4.fna.fbcdn.net&_nc_cat=105&_nc_ohc=2ovs9AVeXPcAX8d3PY8&tp=19&oh=b19a3cd07196a4e5cb38ab3f9aaf84cf&oe=5F8D1BFD",
                        "config_width": 480,
                        "config_height": 853
                    },
                    {
                        "src": "https://instagram.fbkk2-4.fna.fbcdn.net/v/t51.2885-15/e15/p640x640/120898202_2854648384746569_8282414046894556517_n.jpg?_nc_ht=instagram.fbkk2-4.fna.fbcdn.net&_nc_cat=105&_nc_ohc=2ovs9AVeXPcAX8d3PY8&tp=19&oh=5da05402e0e050f112ba689b2789a8e6&oe=5F8CE644",
                        "config_width": 640,
                        "config_height": 1137
                    }
                ]
            },
            {
                "_id": "2413016657629710020",
                "display": "https://instagram.fbkk2-3.fna.fbcdn.net/v/t51.2885-15/fr/e15/p1080x1080/120758339_126692282221437_6367478698801835885_n.jpg?_nc_ht=instagram.fbkk2-3.fna.fbcdn.net&_nc_cat=109&_nc_ohc=bt0pAE9-akoAX9_d6yA&oh=272af73dc1329463c6b2b11371b86378&oe=5F8C8E0D",
                "title": "ต้นฉบับนางงามรักเด็ก",
                "type": "igtv",
                "caption": [
                    {
                        "node": {
                            "text": "#3นาทีคดีดัง นางฟ้าแห่งวงการนางงาม \"ปุ๋ย ภรณ์ทิพย์ นาคหิรัญกนก\" ต้นฉบับนางงามรักเด็ก ผู้คว้าชัยมงกุฎนางงามจักรวาลคนที่ 2 ของไทย กับคำตอบที่ทำให้คนทั่วโลกหลงรัก\n\n#ไทยรัฐออนไลน์"
                        }
                    }
                ],
                "thumbnail_src": "https://instagram.fbkk2-3.fna.fbcdn.net/v/t51.2885-15/sh0.08/e35/c0.420.1080.1080a/s640x640/120758339_126692282221437_6367478698801835885_n.jpg?_nc_ht=instagram.fbkk2-3.fna.fbcdn.net&_nc_cat=109&_nc_ohc=bt0pAE9-akoAX9_d6yA&oh=ae2a64af3b60ed56611cbabd42dc3a09&oe=5F8CAFBE",
                "thumbnail_resources": [
                    {
                        "src": "https://instagram.fbkk2-3.fna.fbcdn.net/v/t51.2885-15/e15/p150x150/120758339_126692282221437_6367478698801835885_n.jpg?_nc_ht=instagram.fbkk2-3.fna.fbcdn.net&_nc_cat=109&_nc_ohc=bt0pAE9-akoAX9_d6yA&tp=19&oh=4e7dfbe8118fdb17fc0b5cbc710f89dd&oe=5F8CCBFA",
                        "config_width": 150,
                        "config_height": 266
                    },
                    {
                        "src": "https://instagram.fbkk2-3.fna.fbcdn.net/v/t51.2885-15/e15/p240x240/120758339_126692282221437_6367478698801835885_n.jpg?_nc_ht=instagram.fbkk2-3.fna.fbcdn.net&_nc_cat=109&_nc_ohc=bt0pAE9-akoAX9_d6yA&tp=19&oh=1f0d7d631dd68129335962263db6fd14&oe=5F8CCB40",
                        "config_width": 240,
                        "config_height": 426
                    },
                    {
                        "src": "https://instagram.fbkk2-3.fna.fbcdn.net/v/t51.2885-15/e15/p320x320/120758339_126692282221437_6367478698801835885_n.jpg?_nc_ht=instagram.fbkk2-3.fna.fbcdn.net&_nc_cat=109&_nc_ohc=bt0pAE9-akoAX9_d6yA&tp=19&oh=610231c624b80f144c70d9a473a8f2f9&oe=5F8CFD42",
                        "config_width": 320,
                        "config_height": 568
                    },
                    {
                        "src": "https://instagram.fbkk2-3.fna.fbcdn.net/v/t51.2885-15/e15/p480x480/120758339_126692282221437_6367478698801835885_n.jpg?_nc_ht=instagram.fbkk2-3.fna.fbcdn.net&_nc_cat=109&_nc_ohc=bt0pAE9-akoAX9_d6yA&tp=19&oh=e024017ccfa93b9dd42c83fc074f4f74&oe=5F8CCAC7",
                        "config_width": 480,
                        "config_height": 853
                    },
                    {
                        "src": "https://instagram.fbkk2-3.fna.fbcdn.net/v/t51.2885-15/sh0.08/e35/p640x640/120758339_126692282221437_6367478698801835885_n.jpg?_nc_ht=instagram.fbkk2-3.fna.fbcdn.net&_nc_cat=109&_nc_ohc=bt0pAE9-akoAX9_d6yA&_nc_tp=25&oh=1a7de205acf52633f04b207730dc087f&oe=5F8CA245",
                        "config_width": 640,
                        "config_height": 1137
                    }
                ]
            },
            {
                "_id": "2412306793436068564",
                "display": "https://instagram.fbkk2-3.fna.fbcdn.net/v/t51.2885-15/e15/120576257_339190860725397_4217530792554273559_n.jpg?_nc_ht=instagram.fbkk2-3.fna.fbcdn.net&_nc_cat=109&_nc_ohc=emN2IBlS8vwAX87R1aZ&_nc_tp=18&oh=54821de9c2c20fe3417636c9bba8d7e0&oe=5F8D1611",
                "title": "ขึ้นเครื่องเสี่ยงโควิด 1%",
                "type": "igtv",
                "caption": [
                    {
                        "node": {
                            "text": "หาคำตอบ \"ทำไมบนเครื่องบินถึงมีโอกาสติดเชื้อโควิด-19 แค่ 1%?\" เมื่อ \"หน้ากาก\" เป็นสิ่งจำเป็นที่ \"ห้ามถอด\" ...จับตาอนาคต \"สายการบิน\" หลังไร้เงินอุ้ม พนักงาน \"ตกงาน\" นับหมื่น\n\n#COVID19"
                        }
                    }
                ],
                "thumbnail_src": "https://instagram.fbkk2-3.fna.fbcdn.net/v/t51.2885-15/e15/c0.280.720.720a/s640x640/120576257_339190860725397_4217530792554273559_n.jpg?_nc_ht=instagram.fbkk2-3.fna.fbcdn.net&_nc_cat=109&_nc_ohc=emN2IBlS8vwAX87R1aZ&tp=16&oh=ff7579f895a17d9c8072fd7d7ad6a3b3&oe=5F8CB396",
                "thumbnail_resources": [
                    {
                        "src": "https://instagram.fbkk2-3.fna.fbcdn.net/v/t51.2885-15/e15/p150x150/120576257_339190860725397_4217530792554273559_n.jpg?_nc_ht=instagram.fbkk2-3.fna.fbcdn.net&_nc_cat=109&_nc_ohc=emN2IBlS8vwAX87R1aZ&tp=19&oh=8393abe654b51e61418402fd57906d04&oe=5F8CBFEC",
                        "config_width": 150,
                        "config_height": 266
                    },
                    {
                        "src": "https://instagram.fbkk2-3.fna.fbcdn.net/v/t51.2885-15/e15/p240x240/120576257_339190860725397_4217530792554273559_n.jpg?_nc_ht=instagram.fbkk2-3.fna.fbcdn.net&_nc_cat=109&_nc_ohc=emN2IBlS8vwAX87R1aZ&tp=19&oh=f430fe89d59830e057b64e2690443237&oe=5F8C93AE",
                        "config_width": 240,
                        "config_height": 426
                    },
                    {
                        "src": "https://instagram.fbkk2-3.fna.fbcdn.net/v/t51.2885-15/e15/p320x320/120576257_339190860725397_4217530792554273559_n.jpg?_nc_ht=instagram.fbkk2-3.fna.fbcdn.net&_nc_cat=109&_nc_ohc=emN2IBlS8vwAX87R1aZ&tp=19&oh=fbda11ad170555073e44ddc5d4bacfc3&oe=5F8C9D14",
                        "config_width": 320,
                        "config_height": 568
                    },
                    {
                        "src": "https://instagram.fbkk2-3.fna.fbcdn.net/v/t51.2885-15/e15/p480x480/120576257_339190860725397_4217530792554273559_n.jpg?_nc_ht=instagram.fbkk2-3.fna.fbcdn.net&_nc_cat=109&_nc_ohc=emN2IBlS8vwAX87R1aZ&tp=19&oh=6043e3b7d4c0de2e1c2aa86dd5bd75ec&oe=5F8CA2D5",
                        "config_width": 480,
                        "config_height": 853
                    },
                    {
                        "src": "https://instagram.fbkk2-3.fna.fbcdn.net/v/t51.2885-15/e15/p640x640/120576257_339190860725397_4217530792554273559_n.jpg?_nc_ht=instagram.fbkk2-3.fna.fbcdn.net&_nc_cat=109&_nc_ohc=emN2IBlS8vwAX87R1aZ&tp=19&oh=d383c621aa9054d98b9ec184ab53b7bb&oe=5F8CEA69",
                        "config_width": 640,
                        "config_height": 1137
                    }
                ]
            },
            {
                "_id": "2411567398250652954",
                "display": "https://instagram.fbkk2-7.fna.fbcdn.net/v/t51.2885-15/e15/120513470_1074718189609134_700003267605679594_n.jpg?_nc_ht=instagram.fbkk2-7.fna.fbcdn.net&_nc_cat=106&_nc_ohc=n49Wger1QLUAX_9lEfZ&_nc_tp=18&oh=fb0db9e38459aad48bf57911b21402eb&oe=5F8C9541",
                "title": "200 ปี ขันลงหิน",
                "type": "igtv",
                "caption": [
                    {
                        "node": {
                            "text": "จะมีผู้สืบทอด หรือสุดท้ายกลายเป็นตำนาน อาชีพเก่าแก่ #ช่างขันลงหิน หรือขันบุ ขันน้ำดื่ม หรือน้ำมันต์ ทรงคุณค่าที่ใช้พิธีต่างๆ ที่ปัจจุบันเหลือโรงงานเพียงแห่งเดียวกับช่าง 6 คน⁣\n⁣\n#LIFESTORY #ขันลงหิน #ไทยรัฐออนไลน์ #Thairath"
                        }
                    }
                ],
                "thumbnail_src": "https://instagram.fbkk2-7.fna.fbcdn.net/v/t51.2885-15/e15/c0.280.720.720a/s640x640/120513470_1074718189609134_700003267605679594_n.jpg?_nc_ht=instagram.fbkk2-7.fna.fbcdn.net&_nc_cat=106&_nc_ohc=n49Wger1QLUAX_9lEfZ&tp=16&oh=6012e98e38a39ed1112317cc13e88100&oe=5F8CD886",
                "thumbnail_resources": [
                    {
                        "src": "https://instagram.fbkk2-7.fna.fbcdn.net/v/t51.2885-15/e15/p150x150/120513470_1074718189609134_700003267605679594_n.jpg?_nc_ht=instagram.fbkk2-7.fna.fbcdn.net&_nc_cat=106&_nc_ohc=n49Wger1QLUAX_9lEfZ&tp=19&oh=a69ceb724f4045eaceefd7513446857c&oe=5F8CA17C",
                        "config_width": 150,
                        "config_height": 266
                    },
                    {
                        "src": "https://instagram.fbkk2-7.fna.fbcdn.net/v/t51.2885-15/e15/p240x240/120513470_1074718189609134_700003267605679594_n.jpg?_nc_ht=instagram.fbkk2-7.fna.fbcdn.net&_nc_cat=106&_nc_ohc=n49Wger1QLUAX_9lEfZ&tp=19&oh=9931042f268318add2a591f5c02d959f&oe=5F8D163E",
                        "config_width": 240,
                        "config_height": 426
                    },
                    {
                        "src": "https://instagram.fbkk2-7.fna.fbcdn.net/v/t51.2885-15/e15/p320x320/120513470_1074718189609134_700003267605679594_n.jpg?_nc_ht=instagram.fbkk2-7.fna.fbcdn.net&_nc_cat=106&_nc_ohc=n49Wger1QLUAX_9lEfZ&tp=19&oh=7e98e1c16a666215c71c8cf2590b7d2f&oe=5F8CD604",
                        "config_width": 320,
                        "config_height": 568
                    },
                    {
                        "src": "https://instagram.fbkk2-7.fna.fbcdn.net/v/t51.2885-15/e15/p480x480/120513470_1074718189609134_700003267605679594_n.jpg?_nc_ht=instagram.fbkk2-7.fna.fbcdn.net&_nc_cat=106&_nc_ohc=n49Wger1QLUAX_9lEfZ&tp=19&oh=e318d0e95ce2e84d23432f9ed59fed7f&oe=5F8D1785",
                        "config_width": 480,
                        "config_height": 853
                    },
                    {
                        "src": "https://instagram.fbkk2-7.fna.fbcdn.net/v/t51.2885-15/e15/p640x640/120513470_1074718189609134_700003267605679594_n.jpg?_nc_ht=instagram.fbkk2-7.fna.fbcdn.net&_nc_cat=106&_nc_ohc=n49Wger1QLUAX_9lEfZ&tp=19&oh=4ec668116f0aec327c602c789fed7e22&oe=5F8CA9F9",
                        "config_width": 640,
                        "config_height": 1137
                    }
                ]
            },
            {
                "_id": "2408849210848731430",
                "display": "https://instagram.fbkk2-7.fna.fbcdn.net/v/t51.2885-15/e15/120218336_412009546454958_7349206849937017972_n.jpg?_nc_ht=instagram.fbkk2-7.fna.fbcdn.net&_nc_cat=106&_nc_ohc=KU5WvtPTg0wAX_cfbeQ&_nc_tp=18&oh=18984d52e0bf2f8feaaf9e1a227d18d4&oe=5F8CFFBE",
                "title": "Thairath Tallk หนุ่ม กรรชัย พลาดสุดในชีวิต",
                "type": "igtv",
                "caption": [
                    {
                        "node": {
                            "text": "ที่แรก หนุ่ม กรรชัย บาดแผลที่สุดในชีวิต เบื้องหลังเรื่องในมุ้ง ‘ติ๊ก-ศรราม’ ‘เราไม่สามารถเข้าไปเสือกทุกเรื่องได้’ \n\nและ ‘ไมค์-ซาร่า’ บทเรียนล้ำค่า ‘ผมไม่อยากเห็นใครเป็นลูกนอกสมรสเหมือนผม’ Thairath Talk ที่แรกที่เดียว\n@kanchai \n\n#เบอร์ใหญ่ต้องThairathTalk #ThairathTalk #ไทยรัฐทอล์ก #ThairathTalk2020 #หนุ่มกรรชัย #กรรชัยกำเนิดพลอย #ไมค์ซาร่า \n#ศรรามติ๊ก\n#ข่าวช่อง3 #โหนกระแส"
                        }
                    }
                ],
                "thumbnail_src": "https://instagram.fbkk2-7.fna.fbcdn.net/v/t51.2885-15/e15/c0.280.720.720a/s640x640/120218336_412009546454958_7349206849937017972_n.jpg?_nc_ht=instagram.fbkk2-7.fna.fbcdn.net&_nc_cat=106&_nc_ohc=KU5WvtPTg0wAX_cfbeQ&tp=16&oh=ccd4bebfe40fbb55c10b39194e325a37&oe=5F8C90F9",
                "thumbnail_resources": [
                    {
                        "src": "https://instagram.fbkk2-7.fna.fbcdn.net/v/t51.2885-15/e15/p150x150/120218336_412009546454958_7349206849937017972_n.jpg?_nc_ht=instagram.fbkk2-7.fna.fbcdn.net&_nc_cat=106&_nc_ohc=KU5WvtPTg0wAX_cfbeQ&tp=19&oh=3f6474f63cb97b41a8d69ddc27282a15&oe=5F8CE0C7",
                        "config_width": 150,
                        "config_height": 266
                    },
                    {
                        "src": "https://instagram.fbkk2-7.fna.fbcdn.net/v/t51.2885-15/e15/p240x240/120218336_412009546454958_7349206849937017972_n.jpg?_nc_ht=instagram.fbkk2-7.fna.fbcdn.net&_nc_cat=106&_nc_ohc=KU5WvtPTg0wAX_cfbeQ&tp=19&oh=33ba226690c791b99cb443af2e7fdf71&oe=5F8CD001",
                        "config_width": 240,
                        "config_height": 426
                    },
                    {
                        "src": "https://instagram.fbkk2-7.fna.fbcdn.net/v/t51.2885-15/e15/p320x320/120218336_412009546454958_7349206849937017972_n.jpg?_nc_ht=instagram.fbkk2-7.fna.fbcdn.net&_nc_cat=106&_nc_ohc=KU5WvtPTg0wAX_cfbeQ&tp=19&oh=9eef77d51764907892643c5e3e8d79b5&oe=5F8CCC3F",
                        "config_width": 320,
                        "config_height": 568
                    },
                    {
                        "src": "https://instagram.fbkk2-7.fna.fbcdn.net/v/t51.2885-15/e15/p480x480/120218336_412009546454958_7349206849937017972_n.jpg?_nc_ht=instagram.fbkk2-7.fna.fbcdn.net&_nc_cat=106&_nc_ohc=KU5WvtPTg0wAX_cfbeQ&tp=19&oh=51c0854f3944a96d065584b5dc21578d&oe=5F8D04BA",
                        "config_width": 480,
                        "config_height": 853
                    },
                    {
                        "src": "https://instagram.fbkk2-7.fna.fbcdn.net/v/t51.2885-15/e15/p640x640/120218336_412009546454958_7349206849937017972_n.jpg?_nc_ht=instagram.fbkk2-7.fna.fbcdn.net&_nc_cat=106&_nc_ohc=KU5WvtPTg0wAX_cfbeQ&tp=19&oh=70e3cf33bb08ccbde8bb8a9ea3e5c146&oe=5F8D1B86",
                        "config_width": 640,
                        "config_height": 1137
                    }
                ]
            }
        ]
    }
}